{
  "company": "a24",
  "fetched_at": "2026-07-12T05:57:36.591129",
  "job_count": 8,
  "jobs": [
    {
      "absolute_url": "https://job-boards.greenhouse.io/a24/jobs/7913662",
      "data_compliance": [
        {
          "type": "gdpr",
          "requires_consent": false,
          "requires_processing_consent": false,
          "requires_retention_consent": false,
          "retention_period": null,
          "demographic_data_consent_applies": false
        }
      ],
      "internal_job_id": 3440326,
      "location": {
        "name": "Los Angeles"
      },
      "metadata": null,
      "id": 7913662,
      "updated_at": "2026-07-09T15:24:59-04:00",
      "requisition_id": null,
      "title": "Digital Marketing",
      "company_name": "A24",
      "first_published": "2026-05-11T14:51:40-04:00",
      "language": "en",
      "application_deadline": null
    },
    {
      "absolute_url": "https://job-boards.greenhouse.io/a24/jobs/8016895",
      "data_compliance": [
        {
          "type": "gdpr",
          "requires_consent": false,
          "requires_processing_consent": false,
          "requires_retention_consent": false,
          "retention_period": null,
          "demographic_data_consent_applies": false
        }
      ],
      "internal_job_id": 3475704,
      "location": {
        "name": "New York"
      },
      "metadata": null,
      "id": 8016895,
      "updated_at": "2026-06-18T15:59:47-04:00",
      "requisition_id": null,
      "title": "Global Licensing Coordinator",
      "company_name": "A24",
      "first_published": "2026-06-18T15:59:47-04:00",
      "language": "en",
      "application_deadline": null
    },
    {
      "absolute_url": "https://job-boards.greenhouse.io/a24/jobs/8009063",
      "data_compliance": [
        {
          "type": "gdpr",
          "requires_consent": false,
          "requires_processing_consent": false,
          "requires_retention_consent": false,
          "retention_period": null,
          "demographic_data_consent_applies": false
        }
      ],
      "internal_job_id": 3472269,
      "location": {
        "name": "Various Locations"
      },
      "metadata": null,
      "id": 8009063,
      "updated_at": "2026-06-15T20:25:50-04:00",
      "requisition_id": null,
      "title": "International Film Sales",
      "company_name": "A24",
      "first_published": "2026-06-15T18:49:52-04:00",
      "language": "en",
      "application_deadline": null
    },
    {
      "absolute_url": "https://job-boards.greenhouse.io/a24/jobs/8049801",
      "data_compliance": [
        {
          "type": "gdpr",
          "requires_consent": false,
          "requires_processing_consent": false,
          "requires_retention_consent": false,
          "retention_period": null,
          "demographic_data_consent_applies": false
        }
      ],
      "internal_job_id": 3488835,
      "location": {
        "name": "Los Angeles"
      },
      "metadata": null,
      "id": 8049801,
      "updated_at": "2026-07-07T17:44:56-04:00",
      "requisition_id": null,
      "title": " Localization Manager",
      "company_name": "A24",
      "first_published": "2026-07-07T17:44:56-04:00",
      "language": "en",
      "application_deadline": null
    },
    {
      "absolute_url": "https://job-boards.greenhouse.io/a24/jobs/7702276",
      "data_compliance": [
        {
          "type": "gdpr",
          "requires_consent": false,
          "requires_processing_consent": false,
          "requires_retention_consent": false,
          "retention_period": null,
          "demographic_data_consent_applies": false
        }
      ],
      "internal_job_id": 3385110,
      "location": {
        "name": "Various Locations"
      },
      "metadata": null,
      "id": 7702276,
      "updated_at": "2026-03-10T19:22:56-04:00",
      "requisition_id": null,
      "title": "Merchandise Production Consultant",
      "company_name": "A24",
      "first_published": "2026-03-10T18:28:41-04:00",
      "language": "en",
      "application_deadline": null
    },
    {
      "absolute_url": "https://job-boards.greenhouse.io/a24/jobs/8036297",
      "data_compliance": [
        {
          "type": "gdpr",
          "requires_consent": false,
          "requires_processing_consent": false,
          "requires_retention_consent": false,
          "retention_period": null,
          "demographic_data_consent_applies": false
        }
      ],
      "internal_job_id": 3483553,
      "location": {
        "name": "Los Angeles"
      },
      "metadata": null,
      "id": 8036297,
      "updated_at": "2026-06-29T14:32:47-04:00",
      "requisition_id": null,
      "title": "Publicist",
      "company_name": "A24",
      "first_published": "2026-06-29T14:32:04-04:00",
      "language": "en",
      "application_deadline": null
    },
    {
      "absolute_url": "https://job-boards.greenhouse.io/a24/jobs/7998374",
      "data_compliance": [
        {
          "type": "gdpr",
          "requires_consent": false,
          "requires_processing_consent": false,
          "requires_retention_consent": false,
          "retention_period": null,
          "demographic_data_consent_applies": false
        }
      ],
      "internal_job_id": 3468909,
      "location": {
        "name": "New York"
      },
      "metadata": null,
      "id": 7998374,
      "updated_at": "2026-06-15T20:25:33-04:00",
      "requisition_id": null,
      "title": "TV Financial Analyst",
      "company_name": "A24",
      "first_published": "2026-06-10T19:53:31-04:00",
      "language": "en",
      "application_deadline": null
    },
    {
      "absolute_url": "https://job-boards.greenhouse.io/a24/jobs/8009145",
      "data_compliance": [
        {
          "type": "gdpr",
          "requires_consent": false,
          "requires_processing_consent": false,
          "requires_retention_consent": false,
          "retention_period": null,
          "demographic_data_consent_applies": false
        }
      ],
      "internal_job_id": 3472558,
      "location": {
        "name": "Various Locations"
      },
      "metadata": null,
      "id": 8009145,
      "updated_at": "2026-06-15T20:23:41-04:00",
      "requisition_id": null,
      "title": "TV Legal Delivery",
      "company_name": "A24",
      "first_published": "2026-06-15T20:23:02-04:00",
      "language": "en",
      "application_deadline": null
    }
  ]
}