{
  "company": "codeandtheory",
  "fetched_at": "2026-02-17T04:56:25.423500",
  "job_count": 25,
  "jobs": [
    {
      "absolute_url": "https://www.codeandtheory.com/careers/8237753002?gh_jid=8237753002",
      "data_compliance": [
        {
          "type": "gdpr",
          "requires_consent": false,
          "requires_processing_consent": false,
          "requires_retention_consent": false,
          "retention_period": null,
          "demographic_data_consent_applies": false
        }
      ],
      "internal_job_id": 6264785002,
      "location": {
        "name": "New York, New York, United States; Remote"
      },
      "metadata": [
        {
          "id": 4095178002,
          "name": "Employment Type",
          "value": null,
          "value_type": "single_select"
        },
        {
          "id": 6769288002,
          "name": "Featured Job for C&T.com?",
          "value": false,
          "value_type": "yes_no"
        }
      ],
      "id": 8237753002,
      "updated_at": "2026-02-10T10:48:48-05:00",
      "requisition_id": "1293",
      "title": "Associate Director, Client Finance",
      "company_name": "Code and Theory",
      "first_published": "2025-10-31T18:34:07-04:00",
      "language": "en"
    },
    {
      "absolute_url": "https://www.codeandtheory.com/careers/8372639002?gh_jid=8372639002",
      "data_compliance": [
        {
          "type": "gdpr",
          "requires_consent": false,
          "requires_processing_consent": false,
          "requires_retention_consent": false,
          "retention_period": null,
          "demographic_data_consent_applies": false
        }
      ],
      "internal_job_id": 6342799002,
      "location": {
        "name": "New York, New York, United States"
      },
      "metadata": [
        {
          "id": 4095178002,
          "name": "Employment Type",
          "value": null,
          "value_type": "single_select"
        },
        {
          "id": 6769288002,
          "name": "Featured Job for C&T.com?",
          "value": false,
          "value_type": "yes_no"
        }
      ],
      "id": 8372639002,
      "updated_at": "2026-02-05T14:04:33-05:00",
      "requisition_id": "1347",
      "title": "Associate Technical Director, Enterprise Systems",
      "company_name": "Code and Theory",
      "first_published": "2026-01-13T12:54:49-05:00",
      "language": "en"
    },
    {
      "absolute_url": "https://www.codeandtheory.com/careers/8302010002?gh_jid=8302010002",
      "data_compliance": [
        {
          "type": "gdpr",
          "requires_consent": false,
          "requires_processing_consent": false,
          "requires_retention_consent": false,
          "retention_period": null,
          "demographic_data_consent_applies": false
        }
      ],
      "internal_job_id": 6313750002,
      "location": {
        "name": "New York, New York, United States"
      },
      "metadata": [
        {
          "id": 4095178002,
          "name": "Employment Type",
          "value": null,
          "value_type": "single_select"
        },
        {
          "id": 6769288002,
          "name": "Featured Job for C&T.com?",
          "value": false,
          "value_type": "yes_no"
        }
      ],
      "id": 8302010002,
      "updated_at": "2026-02-05T10:53:10-05:00",
      "requisition_id": "1310",
      "title": "Brand and Partner Marketing GTM Lead",
      "company_name": "Code and Theory",
      "first_published": "2025-11-20T21:26:37-05:00",
      "language": "en"
    },
    {
      "absolute_url": "https://www.codeandtheory.com/careers/8186729002?gh_jid=8186729002",
      "data_compliance": [
        {
          "type": "gdpr",
          "requires_consent": false,
          "requires_processing_consent": false,
          "requires_retention_consent": false,
          "retention_period": null,
          "demographic_data_consent_applies": false
        }
      ],
      "internal_job_id": 6244600002,
      "location": {
        "name": "Manila, Manila, Philippines"
      },
      "metadata": [
        {
          "id": 4095178002,
          "name": "Employment Type",
          "value": "Full-time",
          "value_type": "single_select"
        },
        {
          "id": 6769288002,
          "name": "Featured Job for C&T.com?",
          "value": false,
          "value_type": "yes_no"
        }
      ],
      "id": 8186729002,
      "updated_at": "2026-02-05T10:53:10-05:00",
      "requisition_id": "1269",
      "title": "Client Finance Coordinator (Manila)",
      "company_name": "Code and Theory",
      "first_published": "2025-09-26T12:45:14-04:00",
      "language": "en"
    },
    {
      "absolute_url": "https://www.codeandtheory.com/careers/7750837002?gh_jid=7750837002",
      "data_compliance": [
        {
          "type": "gdpr",
          "requires_consent": false,
          "requires_processing_consent": false,
          "requires_retention_consent": false,
          "retention_period": null,
          "demographic_data_consent_applies": false
        }
      ],
      "internal_job_id": 6051284002,
      "location": {
        "name": "Manila, Manila, Philippines"
      },
      "metadata": [
        {
          "id": 4095178002,
          "name": "Employment Type",
          "value": "Full-time",
          "value_type": "single_select"
        },
        {
          "id": 6769288002,
          "name": "Featured Job for C&T.com?",
          "value": false,
          "value_type": "yes_no"
        }
      ],
      "id": 7750837002,
      "updated_at": "2026-02-05T10:53:10-05:00",
      "requisition_id": "1046",
      "title": "Digital Producer (Manila)",
      "company_name": "Code and Theory",
      "first_published": "2025-01-23T07:44:00-05:00",
      "language": "en"
    },
    {
      "absolute_url": "https://www.codeandtheory.com/careers/8405771002?gh_jid=8405771002",
      "data_compliance": [
        {
          "type": "gdpr",
          "requires_consent": false,
          "requires_processing_consent": false,
          "requires_retention_consent": false,
          "retention_period": null,
          "demographic_data_consent_applies": false
        }
      ],
      "internal_job_id": 6140667002,
      "location": {
        "name": "Remote"
      },
      "metadata": [
        {
          "id": 4095178002,
          "name": "Employment Type",
          "value": null,
          "value_type": "single_select"
        },
        {
          "id": 6769288002,
          "name": "Featured Job for C&T.com?",
          "value": null,
          "value_type": "yes_no"
        }
      ],
      "id": 8405771002,
      "updated_at": "2026-02-12T17:16:48-05:00",
      "requisition_id": "1157",
      "title": "Director, AI Transformation",
      "company_name": "Code and Theory",
      "first_published": "2026-02-05T10:21:17-05:00",
      "language": "en"
    },
    {
      "absolute_url": "https://www.codeandtheory.com/careers/8338228002?gh_jid=8338228002",
      "data_compliance": [
        {
          "type": "gdpr",
          "requires_consent": false,
          "requires_processing_consent": false,
          "requires_retention_consent": false,
          "retention_period": null,
          "demographic_data_consent_applies": false
        }
      ],
      "internal_job_id": 6329952002,
      "location": {
        "name": "New York, New York, United States"
      },
      "metadata": [
        {
          "id": 4095178002,
          "name": "Employment Type",
          "value": "Full-time",
          "value_type": "single_select"
        },
        {
          "id": 6769288002,
          "name": "Featured Job for C&T.com?",
          "value": false,
          "value_type": "yes_no"
        }
      ],
      "id": 8338228002,
      "updated_at": "2026-02-05T14:33:51-05:00",
      "requisition_id": "1333",
      "title": "Director, Brand Strategy",
      "company_name": "Code and Theory",
      "first_published": "2026-01-09T19:24:52-05:00",
      "language": "en"
    },
    {
      "absolute_url": "https://www.codeandtheory.com/careers/8351905002?gh_jid=8351905002",
      "data_compliance": [
        {
          "type": "gdpr",
          "requires_consent": false,
          "requires_processing_consent": false,
          "requires_retention_consent": false,
          "retention_period": null,
          "demographic_data_consent_applies": false
        }
      ],
      "internal_job_id": 6335395002,
      "location": {
        "name": "New York, New York, United States; Remote"
      },
      "metadata": [
        {
          "id": 4095178002,
          "name": "Employment Type",
          "value": "Full-time",
          "value_type": "single_select"
        },
        {
          "id": 6769288002,
          "name": "Featured Job for C&T.com?",
          "value": null,
          "value_type": "yes_no"
        }
      ],
      "id": 8351905002,
      "updated_at": "2026-02-11T12:17:41-05:00",
      "requisition_id": "1338",
      "title": "Director, Client Engagement",
      "company_name": "Code and Theory",
      "first_published": "2025-12-23T11:56:12-05:00",
      "language": "en"
    },
    {
      "absolute_url": "https://www.codeandtheory.com/careers/8247635002?gh_jid=8247635002",
      "data_compliance": [
        {
          "type": "gdpr",
          "requires_consent": false,
          "requires_processing_consent": false,
          "requires_retention_consent": false,
          "retention_period": null,
          "demographic_data_consent_applies": false
        }
      ],
      "internal_job_id": 6269777002,
      "location": {
        "name": "New York, New York, United States; Remote"
      },
      "metadata": [
        {
          "id": 4095178002,
          "name": "Employment Type",
          "value": "Full-time",
          "value_type": "single_select"
        },
        {
          "id": 6769288002,
          "name": "Featured Job for C&T.com?",
          "value": null,
          "value_type": "yes_no"
        }
      ],
      "id": 8247635002,
      "updated_at": "2026-02-12T15:29:38-05:00",
      "requisition_id": "1298",
      "title": "Director, Solution Engineering",
      "company_name": "Code and Theory",
      "first_published": "2026-02-12T14:14:22-05:00",
      "language": "en"
    },
    {
      "absolute_url": "https://www.codeandtheory.com/careers/8424928002?gh_jid=8424928002",
      "data_compliance": [
        {
          "type": "gdpr",
          "requires_consent": false,
          "requires_processing_consent": false,
          "requires_retention_consent": false,
          "retention_period": null,
          "demographic_data_consent_applies": false
        }
      ],
      "internal_job_id": 6365011002,
      "location": {
        "name": "New York, New York, United States"
      },
      "metadata": [
        {
          "id": 4095178002,
          "name": "Employment Type",
          "value": "Full-time",
          "value_type": "single_select"
        },
        {
          "id": 6769288002,
          "name": "Featured Job for C&T.com?",
          "value": false,
          "value_type": "yes_no"
        }
      ],
      "id": 8424928002,
      "updated_at": "2026-02-16T16:11:35-05:00",
      "requisition_id": "1383",
      "title": "HR Generalist",
      "company_name": "Code and Theory",
      "first_published": "2026-02-16T16:03:35-05:00",
      "language": "en"
    },
    {
      "absolute_url": "https://www.codeandtheory.com/careers/8382950002?gh_jid=8382950002",
      "data_compliance": [
        {
          "type": "gdpr",
          "requires_consent": false,
          "requires_processing_consent": false,
          "requires_retention_consent": false,
          "retention_period": null,
          "demographic_data_consent_applies": false
        }
      ],
      "internal_job_id": 6347033002,
      "location": {
        "name": "Bengaluru, Karnataka, India"
      },
      "metadata": [
        {
          "id": 4095178002,
          "name": "Employment Type",
          "value": "Full-time",
          "value_type": "single_select"
        },
        {
          "id": 6769288002,
          "name": "Featured Job for C&T.com?",
          "value": false,
          "value_type": "yes_no"
        }
      ],
      "id": 8382950002,
      "updated_at": "2026-02-05T14:25:09-05:00",
      "requisition_id": "1355",
      "title": "Lead Backend Engineer, Python (India)",
      "company_name": "Code and Theory",
      "first_published": "2026-01-21T13:27:52-05:00",
      "language": "en"
    },
    {
      "absolute_url": "https://www.codeandtheory.com/careers/8329786002?gh_jid=8329786002",
      "data_compliance": [
        {
          "type": "gdpr",
          "requires_consent": false,
          "requires_processing_consent": false,
          "requires_retention_consent": false,
          "retention_period": null,
          "demographic_data_consent_applies": false
        }
      ],
      "internal_job_id": 6326306002,
      "location": {
        "name": "London, England, United Kingdom"
      },
      "metadata": [
        {
          "id": 4095178002,
          "name": "Employment Type",
          "value": null,
          "value_type": "single_select"
        },
        {
          "id": 6769288002,
          "name": "Featured Job for C&T.com?",
          "value": false,
          "value_type": "yes_no"
        }
      ],
      "id": 8329786002,
      "updated_at": "2026-02-05T10:53:10-05:00",
      "requisition_id": "1325",
      "title": "Lead Data Engineer (London)",
      "company_name": "Code and Theory",
      "first_published": "2025-12-09T13:02:28-05:00",
      "language": "en"
    },
    {
      "absolute_url": "https://www.codeandtheory.com/careers/8390465002?gh_jid=8390465002",
      "data_compliance": [
        {
          "type": "gdpr",
          "requires_consent": false,
          "requires_processing_consent": false,
          "requires_retention_consent": false,
          "retention_period": null,
          "demographic_data_consent_applies": false
        }
      ],
      "internal_job_id": 6349683002,
      "location": {
        "name": "Manila, Manila, Philippines"
      },
      "metadata": [
        {
          "id": 4095178002,
          "name": "Employment Type",
          "value": "Full-time",
          "value_type": "single_select"
        },
        {
          "id": 6769288002,
          "name": "Featured Job for C&T.com?",
          "value": false,
          "value_type": "yes_no"
        }
      ],
      "id": 8390465002,
      "updated_at": "2026-02-09T00:44:37-05:00",
      "requisition_id": "1359",
      "title": "Lead Engineer, Back-End (Manila)",
      "company_name": "Code and Theory",
      "first_published": "2026-01-26T14:14:13-05:00",
      "language": "en"
    },
    {
      "absolute_url": "https://www.codeandtheory.com/careers/8315695002?gh_jid=8315695002",
      "data_compliance": [
        {
          "type": "gdpr",
          "requires_consent": false,
          "requires_processing_consent": false,
          "requires_retention_consent": false,
          "retention_period": null,
          "demographic_data_consent_applies": false
        }
      ],
      "internal_job_id": 6321037002,
      "location": {
        "name": "New York, New York, United States"
      },
      "metadata": [
        {
          "id": 4095178002,
          "name": "Employment Type",
          "value": "Full-time",
          "value_type": "single_select"
        },
        {
          "id": 6769288002,
          "name": "Featured Job for C&T.com?",
          "value": null,
          "value_type": "yes_no"
        }
      ],
      "id": 8315695002,
      "updated_at": "2026-02-05T14:08:05-05:00",
      "requisition_id": "1314",
      "title": "Manager, Client Engagement",
      "company_name": "Code and Theory",
      "first_published": "2025-12-01T13:13:31-05:00",
      "language": "en"
    },
    {
      "absolute_url": "https://www.codeandtheory.com/careers/8199909002?gh_jid=8199909002",
      "data_compliance": [
        {
          "type": "gdpr",
          "requires_consent": false,
          "requires_processing_consent": false,
          "requires_retention_consent": false,
          "retention_period": null,
          "demographic_data_consent_applies": false
        }
      ],
      "internal_job_id": 6249968002,
      "location": {
        "name": "New York, New York, United States"
      },
      "metadata": [
        {
          "id": 4095178002,
          "name": "Employment Type",
          "value": "Full-time",
          "value_type": "single_select"
        },
        {
          "id": 6769288002,
          "name": "Featured Job for C&T.com?",
          "value": null,
          "value_type": "yes_no"
        }
      ],
      "id": 8199909002,
      "updated_at": "2026-02-05T14:27:20-05:00",
      "requisition_id": "1274",
      "title": "Program Director",
      "company_name": "Code and Theory",
      "first_published": "2026-01-25T21:15:41-05:00",
      "language": "en"
    },
    {
      "absolute_url": "https://www.codeandtheory.com/careers/8401105002?gh_jid=8401105002",
      "data_compliance": [
        {
          "type": "gdpr",
          "requires_consent": false,
          "requires_processing_consent": false,
          "requires_retention_consent": false,
          "retention_period": null,
          "demographic_data_consent_applies": false
        }
      ],
      "internal_job_id": 6353990002,
      "location": {
        "name": "New York, New York, United States; Remote"
      },
      "metadata": [
        {
          "id": 4095178002,
          "name": "Employment Type",
          "value": null,
          "value_type": "single_select"
        },
        {
          "id": 6769288002,
          "name": "Featured Job for C&T.com?",
          "value": false,
          "value_type": "yes_no"
        }
      ],
      "id": 8401105002,
      "updated_at": "2026-02-10T12:58:22-05:00",
      "requisition_id": "1368",
      "title": "Quality Engineer",
      "company_name": "Code and Theory",
      "first_published": "2026-02-03T09:09:42-05:00",
      "language": "en"
    },
    {
      "absolute_url": "https://www.codeandtheory.com/careers/8372624002?gh_jid=8372624002",
      "data_compliance": [
        {
          "type": "gdpr",
          "requires_consent": false,
          "requires_processing_consent": false,
          "requires_retention_consent": false,
          "retention_period": null,
          "demographic_data_consent_applies": false
        }
      ],
      "internal_job_id": 6342789002,
      "location": {
        "name": "New York, New York, United States"
      },
      "metadata": [
        {
          "id": 4095178002,
          "name": "Employment Type",
          "value": null,
          "value_type": "single_select"
        },
        {
          "id": 6769288002,
          "name": "Featured Job for C&T.com?",
          "value": false,
          "value_type": "yes_no"
        }
      ],
      "id": 8372624002,
      "updated_at": "2026-02-10T12:54:41-05:00",
      "requisition_id": "1346",
      "title": "Quality Engineering Manager",
      "company_name": "Code and Theory",
      "first_published": "2026-01-13T12:47:48-05:00",
      "language": "en"
    },
    {
      "absolute_url": "https://www.codeandtheory.com/careers/8375713002?gh_jid=8375713002",
      "data_compliance": [
        {
          "type": "gdpr",
          "requires_consent": false,
          "requires_processing_consent": false,
          "requires_retention_consent": false,
          "retention_period": null,
          "demographic_data_consent_applies": false
        }
      ],
      "internal_job_id": 6344076002,
      "location": {
        "name": "Manila, Manila, Philippines"
      },
      "metadata": [
        {
          "id": 4095178002,
          "name": "Employment Type",
          "value": "Full-time",
          "value_type": "single_select"
        },
        {
          "id": 6769288002,
          "name": "Featured Job for C&T.com?",
          "value": null,
          "value_type": "yes_no"
        }
      ],
      "id": 8375713002,
      "updated_at": "2026-02-05T10:53:10-05:00",
      "requisition_id": "1349",
      "title": "Senior Admin Assistant (Manila)",
      "company_name": "Code and Theory",
      "first_published": "2026-01-21T13:23:29-05:00",
      "language": "en"
    },
    {
      "absolute_url": "https://www.codeandtheory.com/careers/8329728002?gh_jid=8329728002",
      "data_compliance": [
        {
          "type": "gdpr",
          "requires_consent": false,
          "requires_processing_consent": false,
          "requires_retention_consent": false,
          "retention_period": null,
          "demographic_data_consent_applies": false
        }
      ],
      "internal_job_id": 6326269002,
      "location": {
        "name": "Bengaluru, Karnataka, India"
      },
      "metadata": [
        {
          "id": 4095178002,
          "name": "Employment Type",
          "value": null,
          "value_type": "single_select"
        },
        {
          "id": 6769288002,
          "name": "Featured Job for C&T.com?",
          "value": false,
          "value_type": "yes_no"
        }
      ],
      "id": 8329728002,
      "updated_at": "2026-02-05T10:53:10-05:00",
      "requisition_id": "1321",
      "title": "Senior Engineer, AI/ML (India)",
      "company_name": "Code and Theory",
      "first_published": "2025-12-09T13:00:57-05:00",
      "language": "en"
    },
    {
      "absolute_url": "https://www.codeandtheory.com/careers/8401162002?gh_jid=8401162002",
      "data_compliance": [
        {
          "type": "gdpr",
          "requires_consent": false,
          "requires_processing_consent": false,
          "requires_retention_consent": false,
          "retention_period": null,
          "demographic_data_consent_applies": false
        }
      ],
      "internal_job_id": 6354013002,
      "location": {
        "name": "New York, New York, United States; Remote"
      },
      "metadata": [
        {
          "id": 4095178002,
          "name": "Employment Type",
          "value": null,
          "value_type": "single_select"
        },
        {
          "id": 6769288002,
          "name": "Featured Job for C&T.com?",
          "value": false,
          "value_type": "yes_no"
        }
      ],
      "id": 8401162002,
      "updated_at": "2026-02-05T14:29:08-05:00",
      "requisition_id": "1369",
      "title": "Senior Engineer, Back-end",
      "company_name": "Code and Theory",
      "first_published": "2026-02-03T09:13:28-05:00",
      "language": "en"
    },
    {
      "absolute_url": "https://www.codeandtheory.com/careers/8395449002?gh_jid=8395449002",
      "data_compliance": [
        {
          "type": "gdpr",
          "requires_consent": false,
          "requires_processing_consent": false,
          "requires_retention_consent": false,
          "retention_period": null,
          "demographic_data_consent_applies": false
        }
      ],
      "internal_job_id": 6351860002,
      "location": {
        "name": "Manila, Manila, Philippines"
      },
      "metadata": [
        {
          "id": 4095178002,
          "name": "Employment Type",
          "value": "Full-time",
          "value_type": "single_select"
        },
        {
          "id": 6769288002,
          "name": "Featured Job for C&T.com?",
          "value": false,
          "value_type": "yes_no"
        }
      ],
      "id": 8395449002,
      "updated_at": "2026-02-05T14:30:45-05:00",
      "requisition_id": "1365",
      "title": "Senior Engineer, Front-end (Manila)",
      "company_name": "Code and Theory",
      "first_published": "2026-01-29T12:23:33-05:00",
      "language": "en"
    },
    {
      "absolute_url": "https://www.codeandtheory.com/careers/8392076002?gh_jid=8392076002",
      "data_compliance": [
        {
          "type": "gdpr",
          "requires_consent": false,
          "requires_processing_consent": false,
          "requires_retention_consent": false,
          "retention_period": null,
          "demographic_data_consent_applies": false
        }
      ],
      "internal_job_id": 6350409002,
      "location": {
        "name": "Manila, Manila, Philippines"
      },
      "metadata": [
        {
          "id": 4095178002,
          "name": "Employment Type",
          "value": "Full-time",
          "value_type": "single_select"
        },
        {
          "id": 6769288002,
          "name": "Featured Job for C&T.com?",
          "value": false,
          "value_type": "yes_no"
        }
      ],
      "id": 8392076002,
      "updated_at": "2026-02-05T10:53:10-05:00",
      "requisition_id": "1361",
      "title": "Senior Engineer, Full-Stack (Manila)",
      "company_name": "Code and Theory",
      "first_published": "2026-01-27T09:49:02-05:00",
      "language": "en"
    },
    {
      "absolute_url": "https://www.codeandtheory.com/careers/8290110002?gh_jid=8290110002",
      "data_compliance": [
        {
          "type": "gdpr",
          "requires_consent": false,
          "requires_processing_consent": false,
          "requires_retention_consent": false,
          "retention_period": null,
          "demographic_data_consent_applies": false
        }
      ],
      "internal_job_id": 6307023002,
      "location": {
        "name": "New York, New York, United States"
      },
      "metadata": [
        {
          "id": 4095178002,
          "name": "Employment Type",
          "value": "Full-time",
          "value_type": "single_select"
        },
        {
          "id": 6769288002,
          "name": "Featured Job for C&T.com?",
          "value": null,
          "value_type": "yes_no"
        }
      ],
      "id": 8290110002,
      "updated_at": "2026-02-09T17:26:40-05:00",
      "requisition_id": "1305",
      "title": "Senior Social Content Creator",
      "company_name": "Code and Theory",
      "first_published": "2026-02-09T17:26:40-05:00",
      "language": "en"
    },
    {
      "absolute_url": "https://www.codeandtheory.com/careers/8329746002?gh_jid=8329746002",
      "data_compliance": [
        {
          "type": "gdpr",
          "requires_consent": false,
          "requires_processing_consent": false,
          "requires_retention_consent": false,
          "retention_period": null,
          "demographic_data_consent_applies": false
        }
      ],
      "internal_job_id": 6326283002,
      "location": {
        "name": "Bengaluru, Karnataka, India"
      },
      "metadata": [
        {
          "id": 4095178002,
          "name": "Employment Type",
          "value": null,
          "value_type": "single_select"
        },
        {
          "id": 6769288002,
          "name": "Featured Job for C&T.com?",
          "value": false,
          "value_type": "yes_no"
        }
      ],
      "id": 8329746002,
      "updated_at": "2026-02-05T10:53:10-05:00",
      "requisition_id": "1322",
      "title": "Solution Architect (India)",
      "company_name": "Code and Theory",
      "first_published": "2025-12-09T13:01:24-05:00",
      "language": "en"
    },
    {
      "absolute_url": "https://www.codeandtheory.com/careers/8369108002?gh_jid=8369108002",
      "data_compliance": [
        {
          "type": "gdpr",
          "requires_consent": false,
          "requires_processing_consent": false,
          "requires_retention_consent": false,
          "retention_period": null,
          "demographic_data_consent_applies": false
        }
      ],
      "internal_job_id": 6341184002,
      "location": {
        "name": "New York, New York, United States"
      },
      "metadata": [
        {
          "id": 4095178002,
          "name": "Employment Type",
          "value": null,
          "value_type": "single_select"
        },
        {
          "id": 6769288002,
          "name": "Featured Job for C&T.com?",
          "value": false,
          "value_type": "yes_no"
        }
      ],
      "id": 8369108002,
      "updated_at": "2026-02-05T14:31:43-05:00",
      "requisition_id": "1343",
      "title": "Technical Director",
      "company_name": "Code and Theory",
      "first_published": "2026-01-09T15:02:33-05:00",
      "language": "en"
    }
  ]
}