{
  "company": "inmobi",
  "fetched_at": "2026-01-15T04:15:19.610632",
  "job_count": 63,
  "jobs": [
    {
      "absolute_url": "https://job-boards.greenhouse.io/inmobi/jobs/7253268",
      "data_compliance": [
        {
          "type": "gdpr",
          "requires_consent": false,
          "requires_processing_consent": false,
          "requires_retention_consent": false,
          "retention_period": null,
          "demographic_data_consent_applies": false
        }
      ],
      "internal_job_id": 3247552,
      "location": {
        "name": "San Mateo, CA"
      },
      "metadata": [
        {
          "id": 164841,
          "name": "Base Country",
          "value": [
            "United States"
          ],
          "value_type": "multi_select"
        },
        {
          "id": 4655336,
          "name": "Backfill ID",
          "value": [
            "harshanand.anandan@inmobi.com"
          ],
          "value_type": "multi_select"
        },
        {
          "id": 29368,
          "name": "Employment Type",
          "value": "Full Time Employee",
          "value_type": "single_select"
        },
        {
          "id": 4617518,
          "name": "Department Name (Career Site)",
          "value": "Technology & Data Science",
          "value_type": "single_select"
        }
      ],
      "id": 7253268,
      "updated_at": "2026-01-12T21:18:12-05:00",
      "requisition_id": "10016",
      "title": "Applied Scientist III",
      "company_name": "InMobi ",
      "first_published": "2025-09-25T00:40:30-04:00",
      "language": "en"
    },
    {
      "absolute_url": "https://job-boards.greenhouse.io/inmobi/jobs/6448631",
      "data_compliance": [
        {
          "type": "gdpr",
          "requires_consent": false,
          "requires_processing_consent": false,
          "requires_retention_consent": false,
          "retention_period": null,
          "demographic_data_consent_applies": false
        }
      ],
      "internal_job_id": 3020055,
      "location": {
        "name": "New Delhi"
      },
      "metadata": [
        {
          "id": 164841,
          "name": "Base Country",
          "value": [
            "India"
          ],
          "value_type": "multi_select"
        },
        {
          "id": 4655336,
          "name": "Backfill ID",
          "value": [
            "NA"
          ],
          "value_type": "multi_select"
        },
        {
          "id": 29368,
          "name": "Employment Type",
          "value": "Full Time Employee",
          "value_type": "single_select"
        },
        {
          "id": 4617518,
          "name": "Department Name (Career Site)",
          "value": "Legal, Finance & Admin",
          "value_type": "single_select"
        }
      ],
      "id": 6448631,
      "updated_at": "2025-12-23T05:17:49-05:00",
      "requisition_id": "8813",
      "title": "Assistant Manager - Processes and Coordination ",
      "company_name": "InMobi ",
      "first_published": "2025-01-06T01:54:17-05:00",
      "language": "en"
    },
    {
      "absolute_url": "https://job-boards.greenhouse.io/inmobi/jobs/7355593",
      "data_compliance": [
        {
          "type": "gdpr",
          "requires_consent": false,
          "requires_processing_consent": false,
          "requires_retention_consent": false,
          "retention_period": null,
          "demographic_data_consent_applies": false
        }
      ],
      "education": "education_required",
      "internal_job_id": 3280771,
      "location": {
        "name": "Bangalore"
      },
      "metadata": [
        {
          "id": 164841,
          "name": "Base Country",
          "value": [
            "India"
          ],
          "value_type": "multi_select"
        },
        {
          "id": 4655336,
          "name": "Backfill ID",
          "value": [
            "NA"
          ],
          "value_type": "multi_select"
        },
        {
          "id": 29368,
          "name": "Employment Type",
          "value": "Full Time Employee",
          "value_type": "single_select"
        },
        {
          "id": 4617518,
          "name": "Department Name (Career Site)",
          "value": "Product Management",
          "value_type": "single_select"
        }
      ],
      "id": 7355593,
      "updated_at": "2025-12-23T05:17:49-05:00",
      "requisition_id": "10124",
      "title": "Associate Product Manager - Central Data Repository",
      "company_name": "InMobi ",
      "first_published": "2025-11-26T01:29:22-05:00",
      "language": "en"
    },
    {
      "absolute_url": "https://job-boards.greenhouse.io/inmobi/jobs/6918622",
      "data_compliance": [
        {
          "type": "gdpr",
          "requires_consent": false,
          "requires_processing_consent": false,
          "requires_retention_consent": false,
          "retention_period": null,
          "demographic_data_consent_applies": false
        }
      ],
      "internal_job_id": 3155659,
      "location": {
        "name": "Bengaluru"
      },
      "metadata": [
        {
          "id": 164841,
          "name": "Base Country",
          "value": [
            "India"
          ],
          "value_type": "multi_select"
        },
        {
          "id": 4655336,
          "name": "Backfill ID",
          "value": [
            "NA"
          ],
          "value_type": "multi_select"
        },
        {
          "id": 29368,
          "name": "Employment Type",
          "value": "Full Time Employee",
          "value_type": "single_select"
        },
        {
          "id": 4617518,
          "name": "Department Name (Career Site)",
          "value": "Technology & Data Science",
          "value_type": "single_select"
        }
      ],
      "id": 6918622,
      "updated_at": "2025-12-23T05:17:49-05:00",
      "requisition_id": "9416",
      "title": "Associate Product Manager - Financial Systems and Transformation",
      "company_name": "InMobi ",
      "first_published": "2025-07-01T06:42:58-04:00",
      "language": "en"
    },
    {
      "absolute_url": "https://job-boards.greenhouse.io/inmobi/jobs/7270523",
      "data_compliance": [
        {
          "type": "gdpr",
          "requires_consent": false,
          "requires_processing_consent": false,
          "requires_retention_consent": false,
          "retention_period": null,
          "demographic_data_consent_applies": false
        }
      ],
      "internal_job_id": 3253286,
      "location": {
        "name": "Tokyo, Japan"
      },
      "metadata": [
        {
          "id": 164841,
          "name": "Base Country",
          "value": [
            "Japan"
          ],
          "value_type": "multi_select"
        },
        {
          "id": 4655336,
          "name": "Backfill ID",
          "value": [
            "NA"
          ],
          "value_type": "multi_select"
        },
        {
          "id": 29368,
          "name": "Employment Type",
          "value": "Full Time Employee",
          "value_type": "single_select"
        },
        {
          "id": 4617518,
          "name": "Department Name (Career Site)",
          "value": "Account Management",
          "value_type": "single_select"
        }
      ],
      "id": 7270523,
      "updated_at": "2025-12-23T05:17:49-05:00",
      "requisition_id": "10036",
      "title": "Brand Account Manager - Tokyo, Japan",
      "company_name": "InMobi ",
      "first_published": "2025-09-23T08:15:48-04:00",
      "language": "en"
    },
    {
      "absolute_url": "https://job-boards.greenhouse.io/inmobi/jobs/7282287",
      "data_compliance": [
        {
          "type": "gdpr",
          "requires_consent": false,
          "requires_processing_consent": false,
          "requires_retention_consent": false,
          "retention_period": null,
          "demographic_data_consent_applies": false
        }
      ],
      "internal_job_id": 3259179,
      "location": {
        "name": "India"
      },
      "metadata": [
        {
          "id": 164841,
          "name": "Base Country",
          "value": [
            "India"
          ],
          "value_type": "multi_select"
        },
        {
          "id": 4655336,
          "name": "Backfill ID",
          "value": [
            "NA"
          ],
          "value_type": "multi_select"
        },
        {
          "id": 29368,
          "name": "Employment Type",
          "value": "Third party Consultant",
          "value_type": "single_select"
        },
        {
          "id": 4617518,
          "name": "Department Name (Career Site)",
          "value": "Legal, Finance & Admin",
          "value_type": "single_select"
        }
      ],
      "id": 7282287,
      "updated_at": "2026-01-06T23:00:58-05:00",
      "requisition_id": "10064",
      "title": "Consultant- Billing and collections",
      "company_name": "InMobi ",
      "first_published": "2026-01-06T23:00:58-05:00",
      "language": "en"
    },
    {
      "absolute_url": "https://job-boards.greenhouse.io/inmobi/jobs/7366663",
      "data_compliance": [
        {
          "type": "gdpr",
          "requires_consent": false,
          "requires_processing_consent": false,
          "requires_retention_consent": false,
          "retention_period": null,
          "demographic_data_consent_applies": false
        }
      ],
      "internal_job_id": 3284938,
      "location": {
        "name": "New York"
      },
      "metadata": [
        {
          "id": 164841,
          "name": "Base Country",
          "value": [
            "United States"
          ],
          "value_type": "multi_select"
        },
        {
          "id": 4655336,
          "name": "Backfill ID",
          "value": [
            "NA"
          ],
          "value_type": "multi_select"
        },
        {
          "id": 29368,
          "name": "Employment Type",
          "value": "Full Time Employee",
          "value_type": "single_select"
        },
        {
          "id": 4617518,
          "name": "Department Name (Career Site)",
          "value": "Sales & Business Development",
          "value_type": "single_select"
        }
      ],
      "id": 7366663,
      "updated_at": "2025-12-23T05:17:49-05:00",
      "requisition_id": "10141",
      "title": "Director, Client Development - Retail",
      "company_name": "InMobi ",
      "first_published": "2025-11-19T18:26:13-05:00",
      "language": "en"
    },
    {
      "absolute_url": "https://job-boards.greenhouse.io/inmobi/jobs/6780169",
      "data_compliance": [
        {
          "type": "gdpr",
          "requires_consent": false,
          "requires_processing_consent": false,
          "requires_retention_consent": false,
          "retention_period": null,
          "demographic_data_consent_applies": false
        }
      ],
      "internal_job_id": 3116419,
      "location": {
        "name": "bangalore"
      },
      "metadata": [
        {
          "id": 164841,
          "name": "Base Country",
          "value": [
            "India"
          ],
          "value_type": "multi_select"
        },
        {
          "id": 4655336,
          "name": "Backfill ID",
          "value": [
            "NA"
          ],
          "value_type": "multi_select"
        },
        {
          "id": 29368,
          "name": "Employment Type",
          "value": "Full Time Employee",
          "value_type": "single_select"
        },
        {
          "id": 4617518,
          "name": "Department Name (Career Site)",
          "value": "Product Management",
          "value_type": "single_select"
        }
      ],
      "id": 6780169,
      "updated_at": "2025-12-23T05:17:49-05:00",
      "requisition_id": "9216",
      "title": "Director Product Management - Marketplace",
      "company_name": "InMobi ",
      "first_published": "2025-06-30T04:36:03-04:00",
      "language": "en"
    },
    {
      "absolute_url": "https://job-boards.greenhouse.io/inmobi/jobs/7172831",
      "data_compliance": [
        {
          "type": "gdpr",
          "requires_consent": false,
          "requires_processing_consent": false,
          "requires_retention_consent": false,
          "retention_period": null,
          "demographic_data_consent_applies": false
        }
      ],
      "internal_job_id": 3199939,
      "location": {
        "name": "Bengaluru"
      },
      "metadata": [
        {
          "id": 164841,
          "name": "Base Country",
          "value": [
            "India"
          ],
          "value_type": "multi_select"
        },
        {
          "id": 4655336,
          "name": "Backfill ID",
          "value": [
            "aishwarya.k@inmobi.com"
          ],
          "value_type": "multi_select"
        },
        {
          "id": 29368,
          "name": "Employment Type",
          "value": "Full Time Employee",
          "value_type": "single_select"
        },
        {
          "id": 4617518,
          "name": "Department Name (Career Site)",
          "value": "Product Management",
          "value_type": "single_select"
        }
      ],
      "id": 7172831,
      "updated_at": "2025-12-23T05:17:49-05:00",
      "requisition_id": "9723",
      "title": "Director - Product Marketing (B2B)",
      "company_name": "InMobi ",
      "first_published": "2025-08-15T15:25:03-04:00",
      "language": "en"
    },
    {
      "absolute_url": "https://job-boards.greenhouse.io/inmobi/jobs/7259249",
      "data_compliance": [
        {
          "type": "gdpr",
          "requires_consent": false,
          "requires_processing_consent": false,
          "requires_retention_consent": false,
          "retention_period": null,
          "demographic_data_consent_applies": false
        }
      ],
      "internal_job_id": 3249747,
      "location": {
        "name": "Jakarta"
      },
      "metadata": [
        {
          "id": 164841,
          "name": "Base Country",
          "value": [
            "Indonesia"
          ],
          "value_type": "multi_select"
        },
        {
          "id": 4655336,
          "name": "Backfill ID",
          "value": [
            "aeryn.shen@inmobi.com"
          ],
          "value_type": "multi_select"
        },
        {
          "id": 29368,
          "name": "Employment Type",
          "value": "Full Time Employee",
          "value_type": "single_select"
        },
        {
          "id": 4617518,
          "name": "Department Name (Career Site)",
          "value": "Marketing",
          "value_type": "single_select"
        }
      ],
      "id": 7259249,
      "updated_at": "2025-12-23T05:17:49-05:00",
      "requisition_id": "10021",
      "title": "Integrated Marketing Lead, SEA",
      "company_name": "InMobi ",
      "first_published": "2025-09-23T07:32:36-04:00",
      "language": "en"
    },
    {
      "absolute_url": "https://job-boards.greenhouse.io/inmobi/jobs/7451607",
      "data_compliance": [
        {
          "type": "gdpr",
          "requires_consent": false,
          "requires_processing_consent": false,
          "requires_retention_consent": false,
          "retention_period": null,
          "demographic_data_consent_applies": false
        }
      ],
      "internal_job_id": 3312237,
      "location": {
        "name": "Mumbai"
      },
      "metadata": [
        {
          "id": 164841,
          "name": "Base Country",
          "value": [
            "India"
          ],
          "value_type": "multi_select"
        },
        {
          "id": 4655336,
          "name": "Backfill ID",
          "value": [
            "anurag.chavhan@inmobi.com"
          ],
          "value_type": "multi_select"
        },
        {
          "id": 29368,
          "name": "Employment Type",
          "value": "Full Time Employee",
          "value_type": "single_select"
        },
        {
          "id": 4617518,
          "name": "Department Name (Career Site)",
          "value": "Account Management",
          "value_type": "single_select"
        }
      ],
      "id": 7451607,
      "updated_at": "2025-12-23T05:17:49-05:00",
      "requisition_id": "10301",
      "title": "Lead - Account Management",
      "company_name": "InMobi ",
      "first_published": "2025-12-17T06:46:38-05:00",
      "language": "en"
    },
    {
      "absolute_url": "https://job-boards.greenhouse.io/inmobi/jobs/7130293",
      "data_compliance": [
        {
          "type": "gdpr",
          "requires_consent": false,
          "requires_processing_consent": false,
          "requires_retention_consent": false,
          "retention_period": null,
          "demographic_data_consent_applies": false
        }
      ],
      "internal_job_id": 3209702,
      "location": {
        "name": "Bangalore"
      },
      "metadata": [
        {
          "id": 164841,
          "name": "Base Country",
          "value": [
            "India"
          ],
          "value_type": "multi_select"
        },
        {
          "id": 4655336,
          "name": "Backfill ID",
          "value": [
            "mdjunaid.omar@inmobi.com"
          ],
          "value_type": "multi_select"
        },
        {
          "id": 29368,
          "name": "Employment Type",
          "value": "Full Time Employee",
          "value_type": "single_select"
        },
        {
          "id": 4617518,
          "name": "Department Name (Career Site)",
          "value": "Account Management",
          "value_type": "single_select"
        }
      ],
      "id": 7130293,
      "updated_at": "2025-12-23T05:17:49-05:00",
      "requisition_id": "9753",
      "title": "Lead Analyst - Programmatic Buying",
      "company_name": "InMobi ",
      "first_published": "2025-08-21T01:42:26-04:00",
      "language": "en"
    },
    {
      "absolute_url": "https://job-boards.greenhouse.io/inmobi/jobs/7019981",
      "data_compliance": [
        {
          "type": "gdpr",
          "requires_consent": false,
          "requires_processing_consent": false,
          "requires_retention_consent": false,
          "retention_period": null,
          "demographic_data_consent_applies": false
        }
      ],
      "internal_job_id": 3181919,
      "location": {
        "name": "Bangalore"
      },
      "metadata": [
        {
          "id": 164841,
          "name": "Base Country",
          "value": [
            "India"
          ],
          "value_type": "multi_select"
        },
        {
          "id": 4655336,
          "name": "Backfill ID",
          "value": [
            "navneet.singh@inmobi.com"
          ],
          "value_type": "multi_select"
        },
        {
          "id": 29368,
          "name": "Employment Type",
          "value": "Full Time Employee",
          "value_type": "single_select"
        },
        {
          "id": 4617518,
          "name": "Department Name (Career Site)",
          "value": "Strategy",
          "value_type": "single_select"
        }
      ],
      "id": 7019981,
      "updated_at": "2026-01-13T08:24:16-05:00",
      "requisition_id": "9578",
      "title": "Lead / Manager - Revenue Operations",
      "company_name": "InMobi ",
      "first_published": "2025-10-08T02:14:11-04:00",
      "language": "en"
    },
    {
      "absolute_url": "https://job-boards.greenhouse.io/inmobi/jobs/7273618",
      "data_compliance": [
        {
          "type": "gdpr",
          "requires_consent": false,
          "requires_processing_consent": false,
          "requires_retention_consent": false,
          "retention_period": null,
          "demographic_data_consent_applies": false
        }
      ],
      "internal_job_id": 3255646,
      "location": {
        "name": "Japan"
      },
      "metadata": [
        {
          "id": 164841,
          "name": "Base Country",
          "value": [
            "Japan"
          ],
          "value_type": "multi_select"
        },
        {
          "id": 4655336,
          "name": "Backfill ID",
          "value": [
            "zyryll.gabriel@inmobi.com"
          ],
          "value_type": "multi_select"
        },
        {
          "id": 29368,
          "name": "Employment Type",
          "value": "Full Time Employee",
          "value_type": "single_select"
        },
        {
          "id": 4617518,
          "name": "Department Name (Career Site)",
          "value": "Technology & Data Science",
          "value_type": "single_select"
        }
      ],
      "id": 7273618,
      "updated_at": "2025-12-23T05:17:49-05:00",
      "requisition_id": "10048",
      "title": "Lead Solutions Engineer",
      "company_name": "InMobi ",
      "first_published": "2025-10-29T09:34:50-04:00",
      "language": "en"
    },
    {
      "absolute_url": "https://job-boards.greenhouse.io/inmobi/jobs/7084423",
      "data_compliance": [
        {
          "type": "gdpr",
          "requires_consent": false,
          "requires_processing_consent": false,
          "requires_retention_consent": false,
          "retention_period": null,
          "demographic_data_consent_applies": false
        }
      ],
      "internal_job_id": 3197044,
      "location": {
        "name": "Bangalore"
      },
      "metadata": [
        {
          "id": 164841,
          "name": "Base Country",
          "value": [
            "India"
          ],
          "value_type": "multi_select"
        },
        {
          "id": 4655336,
          "name": "Backfill ID",
          "value": [
            "NA"
          ],
          "value_type": "multi_select"
        },
        {
          "id": 29368,
          "name": "Employment Type",
          "value": "Full Time Employee",
          "value_type": "single_select"
        },
        {
          "id": 4617518,
          "name": "Department Name (Career Site)",
          "value": "Human Resources",
          "value_type": "single_select"
        }
      ],
      "id": 7084423,
      "updated_at": "2026-01-05T03:55:26-05:00",
      "requisition_id": "9707",
      "title": "Lead - Talent Acquisition",
      "company_name": "InMobi ",
      "first_published": "2025-07-21T06:35:56-04:00",
      "language": "en"
    },
    {
      "absolute_url": "https://job-boards.greenhouse.io/inmobi/jobs/7377047",
      "data_compliance": [
        {
          "type": "gdpr",
          "requires_consent": false,
          "requires_processing_consent": false,
          "requires_retention_consent": false,
          "retention_period": null,
          "demographic_data_consent_applies": false
        }
      ],
      "internal_job_id": 3240951,
      "location": {
        "name": "Bangalore"
      },
      "metadata": [
        {
          "id": 164841,
          "name": "Base Country",
          "value": [
            "India"
          ],
          "value_type": "multi_select"
        },
        {
          "id": 4655336,
          "name": "Backfill ID",
          "value": [
            "prakhar.khare@inmobi.com"
          ],
          "value_type": "multi_select"
        },
        {
          "id": 29368,
          "name": "Employment Type",
          "value": "Full Time Employee",
          "value_type": "single_select"
        },
        {
          "id": 4617518,
          "name": "Department Name (Career Site)",
          "value": "Technology & Data Science",
          "value_type": "single_select"
        }
      ],
      "id": 7377047,
      "updated_at": "2025-12-23T05:17:49-05:00",
      "requisition_id": "9985",
      "title": "Lead – Techstop Operations",
      "company_name": "InMobi ",
      "first_published": "2025-11-04T23:22:36-05:00",
      "language": "en"
    },
    {
      "absolute_url": "https://job-boards.greenhouse.io/inmobi/jobs/7214915",
      "data_compliance": [
        {
          "type": "gdpr",
          "requires_consent": false,
          "requires_processing_consent": false,
          "requires_retention_consent": false,
          "retention_period": null,
          "demographic_data_consent_applies": false
        }
      ],
      "internal_job_id": 3151426,
      "location": {
        "name": "Bengaluru"
      },
      "metadata": [
        {
          "id": 164841,
          "name": "Base Country",
          "value": [
            "India"
          ],
          "value_type": "multi_select"
        },
        {
          "id": 4655336,
          "name": "Backfill ID",
          "value": [
            "NA"
          ],
          "value_type": "multi_select"
        },
        {
          "id": 29368,
          "name": "Employment Type",
          "value": "Full Time Employee",
          "value_type": "single_select"
        },
        {
          "id": 4617518,
          "name": "Department Name (Career Site)",
          "value": "Technology & Data Science",
          "value_type": "single_select"
        }
      ],
      "id": 7214915,
      "updated_at": "2025-12-23T05:17:49-05:00",
      "requisition_id": "9381",
      "title": "Machine Learning Engineer II - Backend",
      "company_name": "InMobi ",
      "first_published": "2025-09-02T07:46:23-04:00",
      "language": "en"
    },
    {
      "absolute_url": "https://job-boards.greenhouse.io/inmobi/jobs/7290555",
      "data_compliance": [
        {
          "type": "gdpr",
          "requires_consent": false,
          "requires_processing_consent": false,
          "requires_retention_consent": false,
          "retention_period": null,
          "demographic_data_consent_applies": false
        }
      ],
      "internal_job_id": 3261750,
      "location": {
        "name": "Bengaluru"
      },
      "metadata": [
        {
          "id": 164841,
          "name": "Base Country",
          "value": [
            "India"
          ],
          "value_type": "multi_select"
        },
        {
          "id": 4655336,
          "name": "Backfill ID",
          "value": [
            "archana.rathor@inmobi.com"
          ],
          "value_type": "multi_select"
        },
        {
          "id": 29368,
          "name": "Employment Type",
          "value": "Full Time Employee",
          "value_type": "single_select"
        },
        {
          "id": 4617518,
          "name": "Department Name (Career Site)",
          "value": "Account Management",
          "value_type": "single_select"
        }
      ],
      "id": 7290555,
      "updated_at": "2025-12-23T05:17:49-05:00",
      "requisition_id": "10070",
      "title": "Manager- Account Management",
      "company_name": "InMobi ",
      "first_published": "2025-10-21T04:06:53-04:00",
      "language": "en"
    },
    {
      "absolute_url": "https://job-boards.greenhouse.io/inmobi/jobs/7309819",
      "data_compliance": [
        {
          "type": "gdpr",
          "requires_consent": false,
          "requires_processing_consent": false,
          "requires_retention_consent": false,
          "retention_period": null,
          "demographic_data_consent_applies": false
        }
      ],
      "internal_job_id": 3268482,
      "location": {
        "name": "Bengaluru"
      },
      "metadata": [
        {
          "id": 164841,
          "name": "Base Country",
          "value": [
            "India"
          ],
          "value_type": "multi_select"
        },
        {
          "id": 4655336,
          "name": "Backfill ID",
          "value": [
            "kanchan.rawat@inmobi.com"
          ],
          "value_type": "multi_select"
        },
        {
          "id": 29368,
          "name": "Employment Type",
          "value": "Full Time Employee",
          "value_type": "single_select"
        },
        {
          "id": 4617518,
          "name": "Department Name (Career Site)",
          "value": "Account Management",
          "value_type": "single_select"
        }
      ],
      "id": 7309819,
      "updated_at": "2025-12-23T05:17:49-05:00",
      "requisition_id": "10082",
      "title": "Manager- Account Management",
      "company_name": "InMobi ",
      "first_published": "2025-10-13T05:41:06-04:00",
      "language": "en"
    },
    {
      "absolute_url": "https://job-boards.greenhouse.io/inmobi/jobs/7364211",
      "data_compliance": [
        {
          "type": "gdpr",
          "requires_consent": false,
          "requires_processing_consent": false,
          "requires_retention_consent": false,
          "retention_period": null,
          "demographic_data_consent_applies": false
        }
      ],
      "internal_job_id": 3284000,
      "location": {
        "name": "New York, NY"
      },
      "metadata": [
        {
          "id": 164841,
          "name": "Base Country",
          "value": [
            "United States"
          ],
          "value_type": "multi_select"
        },
        {
          "id": 4655336,
          "name": "Backfill ID",
          "value": [
            "NA"
          ],
          "value_type": "multi_select"
        },
        {
          "id": 29368,
          "name": "Employment Type",
          "value": "Full Time Employee",
          "value_type": "single_select"
        },
        {
          "id": 4617518,
          "name": "Department Name (Career Site)",
          "value": "Operations",
          "value_type": "single_select"
        }
      ],
      "id": 7364211,
      "updated_at": "2025-12-23T05:17:49-05:00",
      "requisition_id": "10138",
      "title": "Manager, Ad Operations (Demand)",
      "company_name": "InMobi ",
      "first_published": "2025-12-03T22:28:47-05:00",
      "language": "en"
    },
    {
      "absolute_url": "https://job-boards.greenhouse.io/inmobi/jobs/7351457",
      "data_compliance": [
        {
          "type": "gdpr",
          "requires_consent": false,
          "requires_processing_consent": false,
          "requires_retention_consent": false,
          "retention_period": null,
          "demographic_data_consent_applies": false
        }
      ],
      "internal_job_id": 3279500,
      "location": {
        "name": "Bangalore"
      },
      "metadata": [
        {
          "id": 164841,
          "name": "Base Country",
          "value": [
            "India"
          ],
          "value_type": "multi_select"
        },
        {
          "id": 4655336,
          "name": "Backfill ID",
          "value": [
            "NA"
          ],
          "value_type": "multi_select"
        },
        {
          "id": 29368,
          "name": "Employment Type",
          "value": "Full Time Employee",
          "value_type": "single_select"
        },
        {
          "id": 4617518,
          "name": "Department Name (Career Site)",
          "value": "Sales & Business Development",
          "value_type": "single_select"
        }
      ],
      "id": 7351457,
      "updated_at": "2025-12-23T05:17:49-05:00",
      "requisition_id": "10101",
      "title": "Manager - Business Development",
      "company_name": "InMobi ",
      "first_published": "2025-11-03T01:17:56-05:00",
      "language": "en"
    },
    {
      "absolute_url": "https://job-boards.greenhouse.io/inmobi/jobs/7380191",
      "data_compliance": [
        {
          "type": "gdpr",
          "requires_consent": false,
          "requires_processing_consent": false,
          "requires_retention_consent": false,
          "retention_period": null,
          "demographic_data_consent_applies": false
        }
      ],
      "internal_job_id": 3290128,
      "location": {
        "name": "Bangalore"
      },
      "metadata": [
        {
          "id": 164841,
          "name": "Base Country",
          "value": [
            "India"
          ],
          "value_type": "multi_select"
        },
        {
          "id": 4655336,
          "name": "Backfill ID",
          "value": [
            "rajath.krishnan@inmobi.com"
          ],
          "value_type": "multi_select"
        },
        {
          "id": 29368,
          "name": "Employment Type",
          "value": "Full Time Employee",
          "value_type": "single_select"
        },
        {
          "id": 4617518,
          "name": "Department Name (Career Site)",
          "value": "Sales & Business Development",
          "value_type": "single_select"
        }
      ],
      "id": 7380191,
      "updated_at": "2026-01-14T08:32:35-05:00",
      "requisition_id": "10162",
      "title": "Manager - Consumer Insights",
      "company_name": "InMobi ",
      "first_published": "2025-11-23T14:04:50-05:00",
      "language": "en"
    },
    {
      "absolute_url": "https://job-boards.greenhouse.io/inmobi/jobs/6893321",
      "data_compliance": [
        {
          "type": "gdpr",
          "requires_consent": false,
          "requires_processing_consent": false,
          "requires_retention_consent": false,
          "retention_period": null,
          "demographic_data_consent_applies": false
        }
      ],
      "internal_job_id": 3149697,
      "location": {
        "name": "London"
      },
      "metadata": [
        {
          "id": 164841,
          "name": "Base Country",
          "value": [
            "United Kingdom"
          ],
          "value_type": "multi_select"
        },
        {
          "id": 4655336,
          "name": "Backfill ID",
          "value": [
            "calvin.dsouza@inmobi.com"
          ],
          "value_type": "multi_select"
        },
        {
          "id": 29368,
          "name": "Employment Type",
          "value": "Full Time Employee",
          "value_type": "single_select"
        },
        {
          "id": 4617518,
          "name": "Department Name (Career Site)",
          "value": "Account Management",
          "value_type": "single_select"
        }
      ],
      "id": 6893321,
      "updated_at": "2025-12-23T05:17:49-05:00",
      "requisition_id": "9365",
      "title": "Manager - Demand Partnerships",
      "company_name": "InMobi ",
      "first_published": "2025-06-04T02:09:35-04:00",
      "language": "en"
    },
    {
      "absolute_url": "https://job-boards.greenhouse.io/inmobi/jobs/7064141",
      "data_compliance": [
        {
          "type": "gdpr",
          "requires_consent": false,
          "requires_processing_consent": false,
          "requires_retention_consent": false,
          "retention_period": null,
          "demographic_data_consent_applies": false
        }
      ],
      "internal_job_id": 3190967,
      "location": {
        "name": "Bangalore"
      },
      "metadata": [
        {
          "id": 164841,
          "name": "Base Country",
          "value": [
            "India"
          ],
          "value_type": "multi_select"
        },
        {
          "id": 4655336,
          "name": "Backfill ID",
          "value": [
            "NA"
          ],
          "value_type": "multi_select"
        },
        {
          "id": 29368,
          "name": "Employment Type",
          "value": "Full Time Employee",
          "value_type": "single_select"
        },
        {
          "id": 4617518,
          "name": "Department Name (Career Site)",
          "value": "Legal, Finance & Admin",
          "value_type": "single_select"
        }
      ],
      "id": 7064141,
      "updated_at": "2025-12-23T05:17:49-05:00",
      "requisition_id": "9665",
      "title": "Manager - Finance",
      "company_name": "InMobi ",
      "first_published": "2025-07-19T07:28:06-04:00",
      "language": "en"
    },
    {
      "absolute_url": "https://job-boards.greenhouse.io/inmobi/jobs/6476254",
      "data_compliance": [
        {
          "type": "gdpr",
          "requires_consent": false,
          "requires_processing_consent": false,
          "requires_retention_consent": false,
          "retention_period": null,
          "demographic_data_consent_applies": false
        }
      ],
      "internal_job_id": 3028528,
      "location": {
        "name": "New Delhi"
      },
      "metadata": [
        {
          "id": 164841,
          "name": "Base Country",
          "value": [
            "India"
          ],
          "value_type": "multi_select"
        },
        {
          "id": 4655336,
          "name": "Backfill ID",
          "value": [
            "NA"
          ],
          "value_type": "multi_select"
        },
        {
          "id": 29368,
          "name": "Employment Type",
          "value": "Full Time Employee",
          "value_type": "single_select"
        },
        {
          "id": 4617518,
          "name": "Department Name (Career Site)",
          "value": "Legal, Finance & Admin",
          "value_type": "single_select"
        }
      ],
      "id": 6476254,
      "updated_at": "2025-12-23T05:17:49-05:00",
      "requisition_id": "8856",
      "title": "Manager - Government Relations",
      "company_name": "InMobi ",
      "first_published": "2025-01-06T01:45:50-05:00",
      "language": "en"
    },
    {
      "absolute_url": "https://job-boards.greenhouse.io/inmobi/jobs/6780570",
      "data_compliance": [
        {
          "type": "gdpr",
          "requires_consent": false,
          "requires_processing_consent": false,
          "requires_retention_consent": false,
          "retention_period": null,
          "demographic_data_consent_applies": false
        }
      ],
      "internal_job_id": 3116537,
      "location": {
        "name": "Bangalore"
      },
      "metadata": [
        {
          "id": 164841,
          "name": "Base Country",
          "value": [
            "India"
          ],
          "value_type": "multi_select"
        },
        {
          "id": 4655336,
          "name": "Backfill ID",
          "value": [
            "NA"
          ],
          "value_type": "multi_select"
        },
        {
          "id": 29368,
          "name": "Employment Type",
          "value": "Full Time Employee",
          "value_type": "single_select"
        },
        {
          "id": 4617518,
          "name": "Department Name (Career Site)",
          "value": "Human Resources",
          "value_type": "single_select"
        }
      ],
      "id": 6780570,
      "updated_at": "2025-12-23T05:17:49-05:00",
      "requisition_id": "9222",
      "title": "Manager - HRBP",
      "company_name": "InMobi ",
      "first_published": "2025-05-05T03:17:28-04:00",
      "language": "en"
    },
    {
      "absolute_url": "https://job-boards.greenhouse.io/inmobi/jobs/7179702",
      "data_compliance": [
        {
          "type": "gdpr",
          "requires_consent": false,
          "requires_processing_consent": false,
          "requires_retention_consent": false,
          "retention_period": null,
          "demographic_data_consent_applies": false
        }
      ],
      "internal_job_id": 3223304,
      "location": {
        "name": "Bangalore"
      },
      "metadata": [
        {
          "id": 164841,
          "name": "Base Country",
          "value": [
            "India"
          ],
          "value_type": "multi_select"
        },
        {
          "id": 4655336,
          "name": "Backfill ID",
          "value": [
            "gautam.krishnan@inmobi.com"
          ],
          "value_type": "multi_select"
        },
        {
          "id": 29368,
          "name": "Employment Type",
          "value": "Full Time Employee",
          "value_type": "single_select"
        },
        {
          "id": 4617518,
          "name": "Department Name (Career Site)",
          "value": "Product Management",
          "value_type": "single_select"
        }
      ],
      "id": 7179702,
      "updated_at": "2025-12-23T05:17:49-05:00",
      "requisition_id": "9823",
      "title": "Manager - Product Marketing",
      "company_name": "InMobi ",
      "first_published": "2025-09-16T23:06:45-04:00",
      "language": "en"
    },
    {
      "absolute_url": "https://job-boards.greenhouse.io/inmobi/jobs/7370923",
      "data_compliance": [
        {
          "type": "gdpr",
          "requires_consent": false,
          "requires_processing_consent": false,
          "requires_retention_consent": false,
          "retention_period": null,
          "demographic_data_consent_applies": false
        }
      ],
      "internal_job_id": 3286624,
      "location": {
        "name": "New York, NY"
      },
      "metadata": [
        {
          "id": 164841,
          "name": "Base Country",
          "value": [
            "United States"
          ],
          "value_type": "multi_select"
        },
        {
          "id": 4655336,
          "name": "Backfill ID",
          "value": [
            "kyle.shepherd@inmobi.com"
          ],
          "value_type": "multi_select"
        },
        {
          "id": 29368,
          "name": "Employment Type",
          "value": "Full Time Employee",
          "value_type": "single_select"
        },
        {
          "id": 4617518,
          "name": "Department Name (Career Site)",
          "value": "Account Management",
          "value_type": "single_select"
        }
      ],
      "id": 7370923,
      "updated_at": "2025-12-23T05:17:49-05:00",
      "requisition_id": "10145",
      "title": "Manager - Programmatic Trading Development",
      "company_name": "InMobi ",
      "first_published": "2025-12-01T18:53:00-05:00",
      "language": "en"
    },
    {
      "absolute_url": "https://job-boards.greenhouse.io/inmobi/jobs/7212114",
      "data_compliance": [
        {
          "type": "gdpr",
          "requires_consent": false,
          "requires_processing_consent": false,
          "requires_retention_consent": false,
          "retention_period": null,
          "demographic_data_consent_applies": false
        }
      ],
      "internal_job_id": 3215079,
      "location": {
        "name": "London"
      },
      "metadata": [
        {
          "id": 164841,
          "name": "Base Country",
          "value": [
            "United Kingdom"
          ],
          "value_type": "multi_select"
        },
        {
          "id": 4655336,
          "name": "Backfill ID",
          "value": [
            "NA"
          ],
          "value_type": "multi_select"
        },
        {
          "id": 29368,
          "name": "Employment Type",
          "value": "Full Time Employee",
          "value_type": "single_select"
        },
        {
          "id": 4617518,
          "name": "Department Name (Career Site)",
          "value": "Account Management",
          "value_type": "single_select"
        }
      ],
      "id": 7212114,
      "updated_at": "2025-12-23T05:17:49-05:00",
      "requisition_id": "9780",
      "title": "Manager- Programmatic Trading Development",
      "company_name": "InMobi ",
      "first_published": "2025-09-01T07:28:20-04:00",
      "language": "en"
    },
    {
      "absolute_url": "https://job-boards.greenhouse.io/inmobi/jobs/7155107",
      "data_compliance": [
        {
          "type": "gdpr",
          "requires_consent": false,
          "requires_processing_consent": false,
          "requires_retention_consent": false,
          "retention_period": null,
          "demographic_data_consent_applies": false
        }
      ],
      "internal_job_id": 3215191,
      "location": {
        "name": "New Delhi"
      },
      "metadata": [
        {
          "id": 164841,
          "name": "Base Country",
          "value": [
            "India"
          ],
          "value_type": "multi_select"
        },
        {
          "id": 4655336,
          "name": "Backfill ID",
          "value": [
            "ashish.shukla@inmobi.com"
          ],
          "value_type": "multi_select"
        },
        {
          "id": 29368,
          "name": "Employment Type",
          "value": "Full Time Employee",
          "value_type": "single_select"
        },
        {
          "id": 4617518,
          "name": "Department Name (Career Site)",
          "value": "Legal, Finance & Admin",
          "value_type": "single_select"
        }
      ],
      "id": 7155107,
      "updated_at": "2025-12-23T05:17:49-05:00",
      "requisition_id": "9781",
      "title": "Manager - Public Policy and Advocacy",
      "company_name": "InMobi ",
      "first_published": "2025-08-25T00:30:15-04:00",
      "language": "en"
    },
    {
      "absolute_url": "https://job-boards.greenhouse.io/inmobi/jobs/6328749",
      "data_compliance": [
        {
          "type": "gdpr",
          "requires_consent": false,
          "requires_processing_consent": false,
          "requires_retention_consent": false,
          "retention_period": null,
          "demographic_data_consent_applies": false
        }
      ],
      "internal_job_id": 2984543,
      "location": {
        "name": "New Delhi"
      },
      "metadata": [
        {
          "id": 164841,
          "name": "Base Country",
          "value": [
            "India"
          ],
          "value_type": "multi_select"
        },
        {
          "id": 4655336,
          "name": "Backfill ID",
          "value": [
            "NA"
          ],
          "value_type": "multi_select"
        },
        {
          "id": 29368,
          "name": "Employment Type",
          "value": "Full Time Employee",
          "value_type": "single_select"
        },
        {
          "id": 4617518,
          "name": "Department Name (Career Site)",
          "value": "Legal, Finance & Admin",
          "value_type": "single_select"
        }
      ],
      "id": 6328749,
      "updated_at": "2025-12-23T05:17:49-05:00",
      "requisition_id": "8602",
      "title": "Manager - Research & Thought Leadership",
      "company_name": "InMobi ",
      "first_published": "2024-11-08T01:50:12-05:00",
      "language": "en"
    },
    {
      "absolute_url": "https://job-boards.greenhouse.io/inmobi/jobs/7363893",
      "data_compliance": [
        {
          "type": "gdpr",
          "requires_consent": false,
          "requires_processing_consent": false,
          "requires_retention_consent": false,
          "retention_period": null,
          "demographic_data_consent_applies": false
        }
      ],
      "education": "education_optional",
      "internal_job_id": 3283874,
      "location": {
        "name": "New York, NY"
      },
      "metadata": [
        {
          "id": 164841,
          "name": "Base Country",
          "value": [
            "United States"
          ],
          "value_type": "multi_select"
        },
        {
          "id": 4655336,
          "name": "Backfill ID",
          "value": [
            "amanda.pallach@inmobi.com"
          ],
          "value_type": "multi_select"
        },
        {
          "id": 29368,
          "name": "Employment Type",
          "value": "Full Time Employee",
          "value_type": "single_select"
        },
        {
          "id": 4617518,
          "name": "Department Name (Career Site)",
          "value": "Sales & Business Development",
          "value_type": "single_select"
        }
      ],
      "id": 7363893,
      "updated_at": "2025-12-23T05:17:49-05:00",
      "requisition_id": "10135",
      "title": "Partner Manager - Data, Identity, and Addressability",
      "company_name": "InMobi ",
      "first_published": "2025-12-05T06:34:22-05:00",
      "language": "en"
    },
    {
      "absolute_url": "https://job-boards.greenhouse.io/inmobi/jobs/7355595",
      "data_compliance": [
        {
          "type": "gdpr",
          "requires_consent": false,
          "requires_processing_consent": false,
          "requires_retention_consent": false,
          "retention_period": null,
          "demographic_data_consent_applies": false
        }
      ],
      "education": "education_required",
      "internal_job_id": 3280772,
      "location": {
        "name": "Bangalore"
      },
      "metadata": [
        {
          "id": 164841,
          "name": "Base Country",
          "value": [
            "India"
          ],
          "value_type": "multi_select"
        },
        {
          "id": 4655336,
          "name": "Backfill ID",
          "value": [
            "NA"
          ],
          "value_type": "multi_select"
        },
        {
          "id": 29368,
          "name": "Employment Type",
          "value": "Full Time Employee",
          "value_type": "single_select"
        },
        {
          "id": 4617518,
          "name": "Department Name (Career Site)",
          "value": "Product Management",
          "value_type": "single_select"
        }
      ],
      "id": 7355595,
      "updated_at": "2025-12-23T05:17:49-05:00",
      "requisition_id": "10125",
      "title": "Product Manager - Central Data Repository for People Analytics & AI/Automation ",
      "company_name": "InMobi ",
      "first_published": "2025-11-26T01:28:05-05:00",
      "language": "en"
    },
    {
      "absolute_url": "https://job-boards.greenhouse.io/inmobi/jobs/6989467",
      "data_compliance": [
        {
          "type": "gdpr",
          "requires_consent": false,
          "requires_processing_consent": false,
          "requires_retention_consent": false,
          "retention_period": null,
          "demographic_data_consent_applies": false
        }
      ],
      "internal_job_id": 3172755,
      "location": {
        "name": "Chicago"
      },
      "metadata": [
        {
          "id": 164841,
          "name": "Base Country",
          "value": [
            "United States"
          ],
          "value_type": "multi_select"
        },
        {
          "id": 4655336,
          "name": "Backfill ID",
          "value": [
            "charlie.goldberg@inmobi.com"
          ],
          "value_type": "multi_select"
        },
        {
          "id": 29368,
          "name": "Employment Type",
          "value": "Full Time Employee",
          "value_type": "single_select"
        },
        {
          "id": 4617518,
          "name": "Department Name (Career Site)",
          "value": "Sales & Business Development",
          "value_type": "single_select"
        }
      ],
      "id": 6989467,
      "updated_at": "2025-12-23T05:17:49-05:00",
      "requisition_id": "9532",
      "title": "Sales Director",
      "company_name": "InMobi ",
      "first_published": "2025-07-29T16:32:54-04:00",
      "language": "en"
    },
    {
      "absolute_url": "https://job-boards.greenhouse.io/inmobi/jobs/6986982",
      "data_compliance": [
        {
          "type": "gdpr",
          "requires_consent": false,
          "requires_processing_consent": false,
          "requires_retention_consent": false,
          "retention_period": null,
          "demographic_data_consent_applies": false
        }
      ],
      "internal_job_id": 3172017,
      "location": {
        "name": "Tokyo"
      },
      "metadata": [
        {
          "id": 164841,
          "name": "Base Country",
          "value": [
            "Japan"
          ],
          "value_type": "multi_select"
        },
        {
          "id": 4655336,
          "name": "Backfill ID",
          "value": [
            "takuma.okuda@inmobi.com"
          ],
          "value_type": "multi_select"
        },
        {
          "id": 29368,
          "name": "Employment Type",
          "value": "Full Time Employee",
          "value_type": "single_select"
        },
        {
          "id": 4617518,
          "name": "Department Name (Career Site)",
          "value": "Sales & Business Development",
          "value_type": "single_select"
        }
      ],
      "id": 6986982,
      "updated_at": "2025-12-23T05:17:49-05:00",
      "requisition_id": "9528",
      "title": "Sales Manager, Tokyo - Japan",
      "company_name": "InMobi ",
      "first_published": "2025-06-24T03:26:16-04:00",
      "language": "ja"
    },
    {
      "absolute_url": "https://job-boards.greenhouse.io/inmobi/jobs/7405246",
      "data_compliance": [
        {
          "type": "gdpr",
          "requires_consent": false,
          "requires_processing_consent": false,
          "requires_retention_consent": false,
          "retention_period": null,
          "demographic_data_consent_applies": false
        }
      ],
      "internal_job_id": 3299550,
      "location": {
        "name": "Bangalore"
      },
      "metadata": [
        {
          "id": 164841,
          "name": "Base Country",
          "value": [
            "India"
          ],
          "value_type": "multi_select"
        },
        {
          "id": 4655336,
          "name": "Backfill ID",
          "value": [
            "keerthi.thatte@inmobi.com"
          ],
          "value_type": "multi_select"
        },
        {
          "id": 29368,
          "name": "Employment Type",
          "value": "Full Time Employee",
          "value_type": "single_select"
        },
        {
          "id": 4617518,
          "name": "Department Name (Career Site)",
          "value": "Technology & Data Science",
          "value_type": "single_select"
        }
      ],
      "id": 7405246,
      "updated_at": "2025-12-23T05:17:49-05:00",
      "requisition_id": "10189",
      "title": "SDE II - Salesforce",
      "company_name": "InMobi ",
      "first_published": "2025-11-27T05:53:17-05:00",
      "language": "en"
    },
    {
      "absolute_url": "https://job-boards.greenhouse.io/inmobi/jobs/6741379",
      "data_compliance": [
        {
          "type": "gdpr",
          "requires_consent": false,
          "requires_processing_consent": false,
          "requires_retention_consent": false,
          "retention_period": null,
          "demographic_data_consent_applies": false
        }
      ],
      "internal_job_id": 3104583,
      "location": {
        "name": "Bangalore"
      },
      "metadata": [
        {
          "id": 164841,
          "name": "Base Country",
          "value": [
            "India"
          ],
          "value_type": "multi_select"
        },
        {
          "id": 4655336,
          "name": "Backfill ID",
          "value": [
            "NA"
          ],
          "value_type": "multi_select"
        },
        {
          "id": 29368,
          "name": "Employment Type",
          "value": "Full Time Employee",
          "value_type": "single_select"
        },
        {
          "id": 4617518,
          "name": "Department Name (Career Site)",
          "value": "Technology & Data Science",
          "value_type": "single_select"
        }
      ],
      "id": 6741379,
      "updated_at": "2025-12-23T05:17:49-05:00",
      "requisition_id": "9181",
      "title": "SDE IV",
      "company_name": "InMobi ",
      "first_published": "2025-11-12T04:16:18-05:00",
      "language": "en"
    },
    {
      "absolute_url": "https://job-boards.greenhouse.io/inmobi/jobs/7273560",
      "data_compliance": [
        {
          "type": "gdpr",
          "requires_consent": false,
          "requires_processing_consent": false,
          "requires_retention_consent": false,
          "retention_period": null,
          "demographic_data_consent_applies": false
        }
      ],
      "internal_job_id": 3255622,
      "location": {
        "name": "Bangalore"
      },
      "metadata": [
        {
          "id": 164841,
          "name": "Base Country",
          "value": [
            "India"
          ],
          "value_type": "multi_select"
        },
        {
          "id": 4655336,
          "name": "Backfill ID",
          "value": [
            "NA"
          ],
          "value_type": "multi_select"
        },
        {
          "id": 29368,
          "name": "Employment Type",
          "value": "Full Time Employee",
          "value_type": "single_select"
        },
        {
          "id": 4617518,
          "name": "Department Name (Career Site)",
          "value": "Technology & Data Science",
          "value_type": "single_select"
        }
      ],
      "id": 7273560,
      "updated_at": "2025-12-23T05:17:49-05:00",
      "requisition_id": "10046",
      "title": "SDE IV / Associate Manager - Engineering",
      "company_name": "InMobi ",
      "first_published": "2025-12-19T07:25:57-05:00",
      "language": "en"
    },
    {
      "absolute_url": "https://job-boards.greenhouse.io/inmobi/jobs/6919206",
      "data_compliance": [
        {
          "type": "gdpr",
          "requires_consent": false,
          "requires_processing_consent": false,
          "requires_retention_consent": false,
          "retention_period": null,
          "demographic_data_consent_applies": false
        }
      ],
      "internal_job_id": 3155905,
      "location": {
        "name": "Bangalore"
      },
      "metadata": [
        {
          "id": 164841,
          "name": "Base Country",
          "value": [
            "India"
          ],
          "value_type": "multi_select"
        },
        {
          "id": 4655336,
          "name": "Backfill ID",
          "value": [
            "NA"
          ],
          "value_type": "multi_select"
        },
        {
          "id": 29368,
          "name": "Employment Type",
          "value": "Full Time Employee",
          "value_type": "single_select"
        },
        {
          "id": 4617518,
          "name": "Department Name (Career Site)",
          "value": "Technology & Data Science",
          "value_type": "single_select"
        }
      ],
      "id": 6919206,
      "updated_at": "2025-12-23T05:17:49-05:00",
      "requisition_id": "9421",
      "title": "SDE IV - Backend",
      "company_name": "InMobi ",
      "first_published": "2025-11-04T02:35:33-05:00",
      "language": "en"
    },
    {
      "absolute_url": "https://job-boards.greenhouse.io/inmobi/jobs/7076832",
      "data_compliance": [
        {
          "type": "gdpr",
          "requires_consent": false,
          "requires_processing_consent": false,
          "requires_retention_consent": false,
          "retention_period": null,
          "demographic_data_consent_applies": false
        }
      ],
      "internal_job_id": 3194835,
      "location": {
        "name": "Bengaluru"
      },
      "metadata": [
        {
          "id": 164841,
          "name": "Base Country",
          "value": [
            "India"
          ],
          "value_type": "multi_select"
        },
        {
          "id": 4655336,
          "name": "Backfill ID",
          "value": [
            "NA"
          ],
          "value_type": "multi_select"
        },
        {
          "id": 29368,
          "name": "Employment Type",
          "value": "Full Time Employee",
          "value_type": "single_select"
        },
        {
          "id": 4617518,
          "name": "Department Name (Career Site)",
          "value": "Account Management",
          "value_type": "single_select"
        }
      ],
      "id": 7076832,
      "updated_at": "2026-01-12T06:08:16-05:00",
      "requisition_id": "9687",
      "title": "Senior Analyst - Programmatic Buying",
      "company_name": "InMobi ",
      "first_published": "2025-07-29T08:17:04-04:00",
      "language": "en"
    },
    {
      "absolute_url": "https://job-boards.greenhouse.io/inmobi/jobs/6972969",
      "data_compliance": [
        {
          "type": "gdpr",
          "requires_consent": false,
          "requires_processing_consent": false,
          "requires_retention_consent": false,
          "retention_period": null,
          "demographic_data_consent_applies": false
        }
      ],
      "education": "education_required",
      "internal_job_id": 3168832,
      "location": {
        "name": "Bangalore, Karnataka, India"
      },
      "metadata": [
        {
          "id": 164841,
          "name": "Base Country",
          "value": [
            "India"
          ],
          "value_type": "multi_select"
        },
        {
          "id": 4655336,
          "name": "Backfill ID",
          "value": [
            "NA"
          ],
          "value_type": "multi_select"
        },
        {
          "id": 29368,
          "name": "Employment Type",
          "value": "Full Time Employee",
          "value_type": "single_select"
        },
        {
          "id": 4617518,
          "name": "Department Name (Career Site)",
          "value": "Technology & Data Science",
          "value_type": "single_select"
        }
      ],
      "id": 6972969,
      "updated_at": "2025-12-23T05:17:49-05:00",
      "requisition_id": "9510",
      "title": "Senior Application Security Engineer",
      "company_name": "InMobi ",
      "first_published": "2025-08-06T00:19:38-04:00",
      "language": "en"
    },
    {
      "absolute_url": "https://job-boards.greenhouse.io/inmobi/jobs/7525659",
      "data_compliance": [
        {
          "type": "gdpr",
          "requires_consent": false,
          "requires_processing_consent": false,
          "requires_retention_consent": false,
          "retention_period": null,
          "demographic_data_consent_applies": false
        }
      ],
      "internal_job_id": 3330646,
      "location": {
        "name": "Bangalore"
      },
      "metadata": [
        {
          "id": 164841,
          "name": "Base Country",
          "value": [
            "India"
          ],
          "value_type": "multi_select"
        },
        {
          "id": 4655336,
          "name": "Backfill ID",
          "value": [
            "uthra.jithesh@inmobi.com"
          ],
          "value_type": "multi_select"
        },
        {
          "id": 29368,
          "name": "Employment Type",
          "value": "Full Time Employee",
          "value_type": "single_select"
        },
        {
          "id": 4617518,
          "name": "Department Name (Career Site)",
          "value": "Human Resources",
          "value_type": "single_select"
        }
      ],
      "id": 7525659,
      "updated_at": "2026-01-14T01:11:27-05:00",
      "requisition_id": "10375",
      "title": "Senior Associate - Culture",
      "company_name": "InMobi ",
      "first_published": "2026-01-09T05:25:53-05:00",
      "language": "en"
    },
    {
      "absolute_url": "https://job-boards.greenhouse.io/inmobi/jobs/7279065",
      "data_compliance": [
        {
          "type": "gdpr",
          "requires_consent": false,
          "requires_processing_consent": false,
          "requires_retention_consent": false,
          "retention_period": null,
          "demographic_data_consent_applies": false
        }
      ],
      "internal_job_id": 3257797,
      "location": {
        "name": "Bangalore"
      },
      "metadata": [
        {
          "id": 164841,
          "name": "Base Country",
          "value": [
            "India"
          ],
          "value_type": "multi_select"
        },
        {
          "id": 4655336,
          "name": "Backfill ID",
          "value": [
            "NA"
          ],
          "value_type": "multi_select"
        },
        {
          "id": 29368,
          "name": "Employment Type",
          "value": "Full Time Employee",
          "value_type": "single_select"
        },
        {
          "id": 4617518,
          "name": "Department Name (Career Site)",
          "value": "Legal, Finance & Admin",
          "value_type": "single_select"
        }
      ],
      "id": 7279065,
      "updated_at": "2026-01-06T23:16:31-05:00",
      "requisition_id": "10061",
      "title": "Senior Associate - FP&A",
      "company_name": "InMobi ",
      "first_published": "2026-01-06T23:16:31-05:00",
      "language": "en"
    },
    {
      "absolute_url": "https://job-boards.greenhouse.io/inmobi/jobs/7193593",
      "data_compliance": [
        {
          "type": "gdpr",
          "requires_consent": false,
          "requires_processing_consent": false,
          "requires_retention_consent": false,
          "retention_period": null,
          "demographic_data_consent_applies": false
        }
      ],
      "education": "education_optional",
      "internal_job_id": 3228022,
      "location": {
        "name": "London"
      },
      "metadata": [
        {
          "id": 164841,
          "name": "Base Country",
          "value": [
            "United Kingdom"
          ],
          "value_type": "multi_select"
        },
        {
          "id": 4655336,
          "name": "Backfill ID",
          "value": [
            "NA"
          ],
          "value_type": "multi_select"
        },
        {
          "id": 29368,
          "name": "Employment Type",
          "value": "Full Time Employee",
          "value_type": "single_select"
        },
        {
          "id": 4617518,
          "name": "Department Name (Career Site)",
          "value": "Account Management",
          "value_type": "single_select"
        }
      ],
      "id": 7193593,
      "updated_at": "2025-12-23T05:17:49-05:00",
      "requisition_id": "9855",
      "title": "Senior Client Growth Manager",
      "company_name": "InMobi ",
      "first_published": "2025-09-04T01:18:37-04:00",
      "language": "en"
    },
    {
      "absolute_url": "https://job-boards.greenhouse.io/inmobi/jobs/7400562",
      "data_compliance": [
        {
          "type": "gdpr",
          "requires_consent": false,
          "requires_processing_consent": false,
          "requires_retention_consent": false,
          "retention_period": null,
          "demographic_data_consent_applies": false
        }
      ],
      "internal_job_id": 3297963,
      "location": {
        "name": "Bengaluru"
      },
      "metadata": [
        {
          "id": 164841,
          "name": "Base Country",
          "value": [
            "India"
          ],
          "value_type": "multi_select"
        },
        {
          "id": 4655336,
          "name": "Backfill ID",
          "value": [
            "govind.nambiar@inmobi.com"
          ],
          "value_type": "multi_select"
        },
        {
          "id": 29368,
          "name": "Employment Type",
          "value": "Full Time Employee",
          "value_type": "single_select"
        },
        {
          "id": 4617518,
          "name": "Department Name (Career Site)",
          "value": "Account Management",
          "value_type": "single_select"
        }
      ],
      "id": 7400562,
      "updated_at": "2025-12-23T05:17:49-05:00",
      "requisition_id": "10184",
      "title": "Senior Customer Success Associate",
      "company_name": "InMobi ",
      "first_published": "2025-11-28T07:47:27-05:00",
      "language": "en"
    },
    {
      "absolute_url": "https://job-boards.greenhouse.io/inmobi/jobs/7495990",
      "data_compliance": [
        {
          "type": "gdpr",
          "requires_consent": false,
          "requires_processing_consent": false,
          "requires_retention_consent": false,
          "retention_period": null,
          "demographic_data_consent_applies": false
        }
      ],
      "internal_job_id": 3317499,
      "location": {
        "name": "Tokyo, Japan"
      },
      "metadata": [
        {
          "id": 164841,
          "name": "Base Country",
          "value": [
            "Japan"
          ],
          "value_type": "multi_select"
        },
        {
          "id": 4655336,
          "name": "Backfill ID",
          "value": [
            "kenta.tanaka1@inmobi.com"
          ],
          "value_type": "multi_select"
        },
        {
          "id": 29368,
          "name": "Employment Type",
          "value": "Full Time Employee",
          "value_type": "single_select"
        },
        {
          "id": 4617518,
          "name": "Department Name (Career Site)",
          "value": "Sales & Business Development",
          "value_type": "single_select"
        }
      ],
      "id": 7495990,
      "updated_at": "2025-12-24T07:15:50-05:00",
      "requisition_id": "10336",
      "title": "Senior Gaming Business Development Manager, Japan",
      "company_name": "InMobi ",
      "first_published": "2025-12-24T07:15:50-05:00",
      "language": "en"
    },
    {
      "absolute_url": "https://job-boards.greenhouse.io/inmobi/jobs/7137532",
      "data_compliance": [
        {
          "type": "gdpr",
          "requires_consent": false,
          "requires_processing_consent": false,
          "requires_retention_consent": false,
          "retention_period": null,
          "demographic_data_consent_applies": false
        }
      ],
      "internal_job_id": 3211199,
      "location": {
        "name": "India"
      },
      "metadata": [
        {
          "id": 164841,
          "name": "Base Country",
          "value": [
            "India"
          ],
          "value_type": "multi_select"
        },
        {
          "id": 4655336,
          "name": "Backfill ID",
          "value": [
            "ankita.sagar@inmobi.com"
          ],
          "value_type": "multi_select"
        },
        {
          "id": 29368,
          "name": "Employment Type",
          "value": "Full Time Employee",
          "value_type": "single_select"
        },
        {
          "id": 4617518,
          "name": "Department Name (Career Site)",
          "value": "Human Resources",
          "value_type": "single_select"
        }
      ],
      "id": 7137532,
      "updated_at": "2025-12-23T05:17:49-05:00",
      "requisition_id": "9759",
      "title": "Senior HR  Business Partner ",
      "company_name": "InMobi ",
      "first_published": "2025-09-10T03:36:53-04:00",
      "language": "en"
    },
    {
      "absolute_url": "https://job-boards.greenhouse.io/inmobi/jobs/7358497",
      "data_compliance": [
        {
          "type": "gdpr",
          "requires_consent": false,
          "requires_processing_consent": false,
          "requires_retention_consent": false,
          "retention_period": null,
          "demographic_data_consent_applies": false
        }
      ],
      "internal_job_id": 3281911,
      "location": {
        "name": "New York, NY"
      },
      "metadata": [
        {
          "id": 164841,
          "name": "Base Country",
          "value": [
            "United States"
          ],
          "value_type": "multi_select"
        },
        {
          "id": 4655336,
          "name": "Backfill ID",
          "value": [
            "NA"
          ],
          "value_type": "multi_select"
        },
        {
          "id": 29368,
          "name": "Employment Type",
          "value": "Full Time Employee",
          "value_type": "single_select"
        },
        {
          "id": 4617518,
          "name": "Department Name (Career Site)",
          "value": "Sales & Business Development",
          "value_type": "single_select"
        }
      ],
      "id": 7358497,
      "updated_at": "2025-12-23T05:17:49-05:00",
      "requisition_id": "10126",
      "title": "Senior Manager, Client Solutions",
      "company_name": "InMobi ",
      "first_published": "2025-12-04T16:13:54-05:00",
      "language": "en"
    },
    {
      "absolute_url": "https://job-boards.greenhouse.io/inmobi/jobs/7187033",
      "data_compliance": [
        {
          "type": "gdpr",
          "requires_consent": false,
          "requires_processing_consent": false,
          "requires_retention_consent": false,
          "retention_period": null,
          "demographic_data_consent_applies": false
        }
      ],
      "internal_job_id": 3225916,
      "location": {
        "name": "New York"
      },
      "metadata": [
        {
          "id": 164841,
          "name": "Base Country",
          "value": [
            "United States"
          ],
          "value_type": "multi_select"
        },
        {
          "id": 4655336,
          "name": "Backfill ID",
          "value": [
            "sharad.chauhan1@inmobi.com"
          ],
          "value_type": "multi_select"
        },
        {
          "id": 29368,
          "name": "Employment Type",
          "value": "Full Time Employee",
          "value_type": "single_select"
        },
        {
          "id": 4617518,
          "name": "Department Name (Career Site)",
          "value": "Sales & Business Development",
          "value_type": "single_select"
        }
      ],
      "id": 7187033,
      "updated_at": "2026-01-12T18:24:08-05:00",
      "requisition_id": "9840",
      "title": "Senior Manager, Demand Partnerships",
      "company_name": "InMobi ",
      "first_published": "2025-09-05T17:17:27-04:00",
      "language": "en"
    },
    {
      "absolute_url": "https://job-boards.greenhouse.io/inmobi/jobs/7487222",
      "data_compliance": [
        {
          "type": "gdpr",
          "requires_consent": false,
          "requires_processing_consent": false,
          "requires_retention_consent": false,
          "retention_period": null,
          "demographic_data_consent_applies": false
        }
      ],
      "internal_job_id": 3322102,
      "location": {
        "name": "Bangalore"
      },
      "metadata": [
        {
          "id": 164841,
          "name": "Base Country",
          "value": [
            "India"
          ],
          "value_type": "multi_select"
        },
        {
          "id": 4655336,
          "name": "Backfill ID",
          "value": [
            "rajesh.r@inmobi.com"
          ],
          "value_type": "multi_select"
        },
        {
          "id": 29368,
          "name": "Employment Type",
          "value": "FTE",
          "value_type": "single_select"
        },
        {
          "id": 4617518,
          "name": "Department Name (Career Site)",
          "value": "Legal, Finance & Admin",
          "value_type": "single_select"
        }
      ],
      "id": 7487222,
      "updated_at": "2026-01-12T01:38:42-05:00",
      "requisition_id": "10350",
      "title": "Senior Manager - Procurement",
      "company_name": "InMobi ",
      "first_published": "2026-01-12T01:38:42-05:00",
      "language": "en"
    },
    {
      "absolute_url": "https://job-boards.greenhouse.io/inmobi/jobs/7179729",
      "data_compliance": [
        {
          "type": "gdpr",
          "requires_consent": false,
          "requires_processing_consent": false,
          "requires_retention_consent": false,
          "retention_period": null,
          "demographic_data_consent_applies": false
        }
      ],
      "internal_job_id": 3223311,
      "location": {
        "name": "Bangalore"
      },
      "metadata": [
        {
          "id": 164841,
          "name": "Base Country",
          "value": [
            "India"
          ],
          "value_type": "multi_select"
        },
        {
          "id": 4655336,
          "name": "Backfill ID",
          "value": [
            "chintan.joshi@inmobi.com"
          ],
          "value_type": "multi_select"
        },
        {
          "id": 29368,
          "name": "Employment Type",
          "value": "Full Time Employee",
          "value_type": "single_select"
        },
        {
          "id": 4617518,
          "name": "Department Name (Career Site)",
          "value": "Strategy",
          "value_type": "single_select"
        }
      ],
      "id": 7179729,
      "updated_at": "2025-12-23T05:17:49-05:00",
      "requisition_id": "9825",
      "title": "Senior Manager: Revenue Operations (Techstack & Governance)",
      "company_name": "InMobi ",
      "first_published": "2025-09-03T05:18:28-04:00",
      "language": "en"
    },
    {
      "absolute_url": "https://job-boards.greenhouse.io/inmobi/jobs/6843668",
      "data_compliance": [
        {
          "type": "gdpr",
          "requires_consent": false,
          "requires_processing_consent": false,
          "requires_retention_consent": false,
          "retention_period": null,
          "demographic_data_consent_applies": false
        }
      ],
      "internal_job_id": 3133243,
      "location": {
        "name": "Bangalore"
      },
      "metadata": [
        {
          "id": 164841,
          "name": "Base Country",
          "value": [
            "India"
          ],
          "value_type": "multi_select"
        },
        {
          "id": 4655336,
          "name": "Backfill ID",
          "value": [
            "NA"
          ],
          "value_type": "multi_select"
        },
        {
          "id": 29368,
          "name": "Employment Type",
          "value": "Full Time Employee",
          "value_type": "single_select"
        },
        {
          "id": 4617518,
          "name": "Department Name (Career Site)",
          "value": "Strategy",
          "value_type": "single_select"
        }
      ],
      "id": 6843668,
      "updated_at": "2025-12-23T05:17:49-05:00",
      "requisition_id": "9287",
      "title": "Senior Manager - Strategy & Operations",
      "company_name": "InMobi ",
      "first_published": "2025-06-18T08:01:19-04:00",
      "language": "en"
    },
    {
      "absolute_url": "https://job-boards.greenhouse.io/inmobi/jobs/7191369",
      "data_compliance": [
        {
          "type": "gdpr",
          "requires_consent": false,
          "requires_processing_consent": false,
          "requires_retention_consent": false,
          "retention_period": null,
          "demographic_data_consent_applies": false
        }
      ],
      "internal_job_id": 3227310,
      "location": {
        "name": "San Mateo / New York"
      },
      "metadata": [
        {
          "id": 164841,
          "name": "Base Country",
          "value": [
            "United States"
          ],
          "value_type": "multi_select"
        },
        {
          "id": 4655336,
          "name": "Backfill ID",
          "value": [
            "NA"
          ],
          "value_type": "multi_select"
        },
        {
          "id": 29368,
          "name": "Employment Type",
          "value": "Full Time Employee",
          "value_type": "single_select"
        },
        {
          "id": 4617518,
          "name": "Department Name (Career Site)",
          "value": "Product Management",
          "value_type": "single_select"
        }
      ],
      "id": 7191369,
      "updated_at": "2025-12-23T05:17:49-05:00",
      "requisition_id": "9849",
      "title": "Senior Product Manager ",
      "company_name": "InMobi ",
      "first_published": "2025-11-26T04:04:26-05:00",
      "language": "en"
    },
    {
      "absolute_url": "https://job-boards.greenhouse.io/inmobi/jobs/7337428",
      "data_compliance": [
        {
          "type": "gdpr",
          "requires_consent": false,
          "requires_processing_consent": false,
          "requires_retention_consent": false,
          "retention_period": null,
          "demographic_data_consent_applies": false
        }
      ],
      "education": "education_required",
      "internal_job_id": 3274300,
      "location": {
        "name": "Bangalore"
      },
      "metadata": [
        {
          "id": 164841,
          "name": "Base Country",
          "value": [
            "India"
          ],
          "value_type": "multi_select"
        },
        {
          "id": 4655336,
          "name": "Backfill ID",
          "value": [
            "NA"
          ],
          "value_type": "multi_select"
        },
        {
          "id": 29368,
          "name": "Employment Type",
          "value": "Full Time Employee",
          "value_type": "single_select"
        },
        {
          "id": 4617518,
          "name": "Department Name (Career Site)",
          "value": "Product Management",
          "value_type": "single_select"
        }
      ],
      "id": 7337428,
      "updated_at": "2025-12-23T05:17:49-05:00",
      "requisition_id": "10096",
      "title": "Senior Product Manager - Central Data Repository & Data Platform AI",
      "company_name": "InMobi ",
      "first_published": "2025-10-20T02:14:22-04:00",
      "language": "en"
    },
    {
      "absolute_url": "https://job-boards.greenhouse.io/inmobi/jobs/7298379",
      "data_compliance": [
        {
          "type": "gdpr",
          "requires_consent": false,
          "requires_processing_consent": false,
          "requires_retention_consent": false,
          "retention_period": null,
          "demographic_data_consent_applies": false
        }
      ],
      "internal_job_id": 3264779,
      "location": {
        "name": "New York, NY"
      },
      "metadata": [
        {
          "id": 164841,
          "name": "Base Country",
          "value": [
            "United States"
          ],
          "value_type": "multi_select"
        },
        {
          "id": 4655336,
          "name": "Backfill ID",
          "value": [
            "varna.shanker@inmobi.com"
          ],
          "value_type": "multi_select"
        },
        {
          "id": 29368,
          "name": "Employment Type",
          "value": "Full Time Employee",
          "value_type": "single_select"
        },
        {
          "id": 4617518,
          "name": "Department Name (Career Site)",
          "value": "Sales & Business Development",
          "value_type": "single_select"
        }
      ],
      "id": 7298379,
      "updated_at": "2025-12-23T05:17:49-05:00",
      "requisition_id": "10073",
      "title": "Senior Publisher Development Manager",
      "company_name": "InMobi ",
      "first_published": "2025-11-25T12:33:12-05:00",
      "language": "en"
    },
    {
      "absolute_url": "https://job-boards.greenhouse.io/inmobi/jobs/7282061",
      "data_compliance": [
        {
          "type": "gdpr",
          "requires_consent": false,
          "requires_processing_consent": false,
          "requires_retention_consent": false,
          "retention_period": null,
          "demographic_data_consent_applies": false
        }
      ],
      "internal_job_id": 3253375,
      "location": {
        "name": "Tokyo, Japan"
      },
      "metadata": [
        {
          "id": 164841,
          "name": "Base Country",
          "value": [
            "Japan"
          ],
          "value_type": "multi_select"
        },
        {
          "id": 4655336,
          "name": "Backfill ID",
          "value": [
            "NA"
          ],
          "value_type": "multi_select"
        },
        {
          "id": 29368,
          "name": "Employment Type",
          "value": "Full Time Employee",
          "value_type": "single_select"
        },
        {
          "id": 4617518,
          "name": "Department Name (Career Site)",
          "value": "Sales & Business Development",
          "value_type": "single_select"
        }
      ],
      "id": 7282061,
      "updated_at": "2025-12-23T05:17:49-05:00",
      "requisition_id": "10037",
      "title": "Senior Sales Manager - Tokyo, Japan",
      "company_name": "InMobi ",
      "first_published": "2025-09-28T22:13:22-04:00",
      "language": "en"
    },
    {
      "absolute_url": "https://job-boards.greenhouse.io/inmobi/jobs/6866680",
      "data_compliance": [
        {
          "type": "gdpr",
          "requires_consent": false,
          "requires_processing_consent": false,
          "requires_retention_consent": false,
          "retention_period": null,
          "demographic_data_consent_applies": false
        }
      ],
      "internal_job_id": 3140659,
      "location": {
        "name": "New York, NY"
      },
      "metadata": [
        {
          "id": 164841,
          "name": "Base Country",
          "value": [
            "United States"
          ],
          "value_type": "multi_select"
        },
        {
          "id": 4655336,
          "name": "Backfill ID",
          "value": [
            "NA"
          ],
          "value_type": "multi_select"
        },
        {
          "id": 29368,
          "name": "Employment Type",
          "value": "Full Time Employee",
          "value_type": "single_select"
        },
        {
          "id": 4617518,
          "name": "Department Name (Career Site)",
          "value": "Sales & Business Development",
          "value_type": "single_select"
        }
      ],
      "id": 6866680,
      "updated_at": "2025-12-23T05:17:49-05:00",
      "requisition_id": "9317",
      "title": "Sr. Sales Manager",
      "company_name": "InMobi ",
      "first_published": "2025-05-08T09:44:59-04:00",
      "language": "en"
    },
    {
      "absolute_url": "https://job-boards.greenhouse.io/inmobi/jobs/7412582",
      "data_compliance": [
        {
          "type": "gdpr",
          "requires_consent": false,
          "requires_processing_consent": false,
          "requires_retention_consent": false,
          "retention_period": null,
          "demographic_data_consent_applies": false
        }
      ],
      "internal_job_id": 3302529,
      "location": {
        "name": "Lucknow"
      },
      "metadata": [
        {
          "id": 164841,
          "name": "Base Country",
          "value": [
            "India"
          ],
          "value_type": "multi_select"
        },
        {
          "id": 4655336,
          "name": "Backfill ID",
          "value": [
            "NA"
          ],
          "value_type": "multi_select"
        },
        {
          "id": 29368,
          "name": "Employment Type",
          "value": "Full Time Employee",
          "value_type": "single_select"
        },
        {
          "id": 4617518,
          "name": "Department Name (Career Site)",
          "value": "Technology & Data Science",
          "value_type": "single_select"
        }
      ],
      "id": 7412582,
      "updated_at": "2026-01-12T02:51:03-05:00",
      "requisition_id": "10225",
      "title": "Staff Applied Scientist I",
      "company_name": "InMobi ",
      "first_published": "2025-11-26T01:37:56-05:00",
      "language": "en"
    },
    {
      "absolute_url": "https://job-boards.greenhouse.io/inmobi/jobs/7216575",
      "data_compliance": [
        {
          "type": "gdpr",
          "requires_consent": false,
          "requires_processing_consent": false,
          "requires_retention_consent": false,
          "retention_period": null,
          "demographic_data_consent_applies": false
        }
      ],
      "internal_job_id": 3236421,
      "location": {
        "name": "Bangalore"
      },
      "metadata": [
        {
          "id": 164841,
          "name": "Base Country",
          "value": [
            "Singapore"
          ],
          "value_type": "multi_select"
        },
        {
          "id": 4655336,
          "name": "Backfill ID",
          "value": [
            "krishna.chaitanya@inmobi.com"
          ],
          "value_type": "multi_select"
        },
        {
          "id": 29368,
          "name": "Employment Type",
          "value": "Direct Consultant",
          "value_type": "single_select"
        },
        {
          "id": 4617518,
          "name": "Department Name (Career Site)",
          "value": "Technology & Data Science",
          "value_type": "single_select"
        }
      ],
      "id": 7216575,
      "updated_at": "2026-01-09T00:28:48-05:00",
      "requisition_id": "9973",
      "title": "Staff Applied Scientist I",
      "company_name": "InMobi ",
      "first_published": "2025-09-19T02:30:46-04:00",
      "language": "en"
    },
    {
      "absolute_url": "https://job-boards.greenhouse.io/inmobi/jobs/6703420",
      "data_compliance": [
        {
          "type": "gdpr",
          "requires_consent": false,
          "requires_processing_consent": false,
          "requires_retention_consent": false,
          "retention_period": null,
          "demographic_data_consent_applies": false
        }
      ],
      "internal_job_id": 3095450,
      "location": {
        "name": "Bangalore"
      },
      "metadata": [
        {
          "id": 164841,
          "name": "Base Country",
          "value": [
            "India"
          ],
          "value_type": "multi_select"
        },
        {
          "id": 4655336,
          "name": "Backfill ID",
          "value": [
            "NA"
          ],
          "value_type": "multi_select"
        },
        {
          "id": 29368,
          "name": "Employment Type",
          "value": "Full Time Employee",
          "value_type": "single_select"
        },
        {
          "id": 4617518,
          "name": "Department Name (Career Site)",
          "value": "Technology & Data Science",
          "value_type": "single_select"
        }
      ],
      "id": 6703420,
      "updated_at": "2025-12-23T05:17:49-05:00",
      "requisition_id": "9117",
      "title": "Staff Data Scientist I",
      "company_name": "InMobi ",
      "first_published": "2025-04-22T08:42:33-04:00",
      "language": "en"
    },
    {
      "absolute_url": "https://job-boards.greenhouse.io/inmobi/jobs/6761066",
      "data_compliance": [
        {
          "type": "gdpr",
          "requires_consent": false,
          "requires_processing_consent": false,
          "requires_retention_consent": false,
          "retention_period": null,
          "demographic_data_consent_applies": false
        }
      ],
      "internal_job_id": 3110875,
      "location": {
        "name": "Bangalore"
      },
      "metadata": [
        {
          "id": 164841,
          "name": "Base Country",
          "value": [
            "India"
          ],
          "value_type": "multi_select"
        },
        {
          "id": 4655336,
          "name": "Backfill ID",
          "value": [
            "NA"
          ],
          "value_type": "multi_select"
        },
        {
          "id": 29368,
          "name": "Employment Type",
          "value": "Full Time Employee",
          "value_type": "single_select"
        },
        {
          "id": 4617518,
          "name": "Department Name (Career Site)",
          "value": "Technology & Data Science",
          "value_type": "single_select"
        }
      ],
      "id": 6761066,
      "updated_at": "2025-12-23T05:17:49-05:00",
      "requisition_id": "9196",
      "title": "Staff Engineer I",
      "company_name": "InMobi ",
      "first_published": "2025-09-02T07:40:10-04:00",
      "language": "en"
    },
    {
      "absolute_url": "https://job-boards.greenhouse.io/inmobi/jobs/7452014",
      "data_compliance": [
        {
          "type": "gdpr",
          "requires_consent": false,
          "requires_processing_consent": false,
          "requires_retention_consent": false,
          "retention_period": null,
          "demographic_data_consent_applies": false
        }
      ],
      "internal_job_id": 3312388,
      "location": {
        "name": "New York"
      },
      "metadata": [
        {
          "id": 164841,
          "name": "Base Country",
          "value": [
            "United States"
          ],
          "value_type": "multi_select"
        },
        {
          "id": 4655336,
          "name": "Backfill ID",
          "value": [
            "NA"
          ],
          "value_type": "multi_select"
        },
        {
          "id": 29368,
          "name": "Employment Type",
          "value": "Full Time Employee",
          "value_type": "single_select"
        },
        {
          "id": 4617518,
          "name": "Department Name (Career Site)",
          "value": "Marketing",
          "value_type": "single_select"
        }
      ],
      "id": 7452014,
      "updated_at": "2026-01-09T08:05:04-05:00",
      "requisition_id": "10305",
      "title": "Vice President - Global Events",
      "company_name": "InMobi ",
      "first_published": "2025-12-12T13:30:10-05:00",
      "language": "en"
    },
    {
      "absolute_url": "https://job-boards.greenhouse.io/inmobi/jobs/7405036",
      "data_compliance": [
        {
          "type": "gdpr",
          "requires_consent": false,
          "requires_processing_consent": false,
          "requires_retention_consent": false,
          "retention_period": null,
          "demographic_data_consent_applies": false
        }
      ],
      "internal_job_id": 3299458,
      "location": {
        "name": "New York"
      },
      "metadata": [
        {
          "id": 164841,
          "name": "Base Country",
          "value": [
            "United States"
          ],
          "value_type": "multi_select"
        },
        {
          "id": 4655336,
          "name": "Backfill ID",
          "value": [
            "NA"
          ],
          "value_type": "multi_select"
        },
        {
          "id": 29368,
          "name": "Employment Type",
          "value": "FTE",
          "value_type": "single_select"
        },
        {
          "id": 4617518,
          "name": "Department Name (Career Site)",
          "value": "Strategy",
          "value_type": "single_select"
        }
      ],
      "id": 7405036,
      "updated_at": "2026-01-12T08:35:33-05:00",
      "requisition_id": "10188",
      "title": "VP – Strategic Partnerships",
      "company_name": "InMobi ",
      "first_published": "2026-01-12T08:35:33-05:00",
      "language": "en"
    }
  ]
}