{
  "company": "nurix",
  "fetched_at": "2026-05-16T06:02:58.091995",
  "job_count": 15,
  "jobs": [
    {
      "absolute_url": "https://job-boards.greenhouse.io/nurix/jobs/8535914002",
      "data_compliance": [
        {
          "type": "gdpr",
          "requires_consent": false,
          "requires_processing_consent": false,
          "requires_retention_consent": false,
          "retention_period": null,
          "demographic_data_consent_applies": false
        }
      ],
      "internal_job_id": 6409064002,
      "location": {
        "name": "Brisbane, CA"
      },
      "metadata": null,
      "id": 8535914002,
      "updated_at": "2026-05-05T16:37:06-04:00",
      "requisition_id": null,
      "title": "Associate Director, Computer Systems Assurance (Quality)",
      "company_name": "Nurix",
      "first_published": "2026-05-05T16:15:31-04:00",
      "language": "en",
      "application_deadline": null
    },
    {
      "absolute_url": "https://job-boards.greenhouse.io/nurix/jobs/8365519002",
      "data_compliance": [
        {
          "type": "gdpr",
          "requires_consent": false,
          "requires_processing_consent": false,
          "requires_retention_consent": false,
          "retention_period": null,
          "demographic_data_consent_applies": false
        }
      ],
      "internal_job_id": 6339820002,
      "location": {
        "name": "Brisbane, CA"
      },
      "metadata": null,
      "id": 8365519002,
      "updated_at": "2026-04-04T13:15:09-04:00",
      "requisition_id": "530-2601",
      "title": "Associate Director, Quantitative Pharmacology and Pharmacometrics",
      "company_name": "Nurix",
      "first_published": "2026-01-07T23:56:02-05:00",
      "language": "en",
      "application_deadline": null
    },
    {
      "absolute_url": "https://job-boards.greenhouse.io/nurix/jobs/8444943002",
      "data_compliance": [
        {
          "type": "gdpr",
          "requires_consent": false,
          "requires_processing_consent": false,
          "requires_retention_consent": false,
          "retention_period": null,
          "demographic_data_consent_applies": false
        }
      ],
      "internal_job_id": 6373425002,
      "location": {
        "name": "Brisbane, CA "
      },
      "metadata": null,
      "id": 8444943002,
      "updated_at": "2026-05-14T12:09:33-04:00",
      "requisition_id": "520-2606C",
      "title": "Biosample Manager",
      "company_name": "Nurix",
      "first_published": "2026-05-02T11:53:27-04:00",
      "language": "en",
      "application_deadline": null
    },
    {
      "absolute_url": "https://job-boards.greenhouse.io/nurix/jobs/8389567002",
      "data_compliance": [
        {
          "type": "gdpr",
          "requires_consent": false,
          "requires_processing_consent": false,
          "requires_retention_consent": false,
          "retention_period": null,
          "demographic_data_consent_applies": false
        }
      ],
      "internal_job_id": 6349286002,
      "location": {
        "name": "Brisbane, CA"
      },
      "metadata": null,
      "id": 8389567002,
      "updated_at": "2026-03-27T18:00:29-04:00",
      "requisition_id": "630-2006",
      "title": "Director of IT Operations",
      "company_name": "Nurix",
      "first_published": "2026-03-04T17:33:29-05:00",
      "language": "en",
      "application_deadline": null
    },
    {
      "absolute_url": "https://job-boards.greenhouse.io/nurix/jobs/8535319002",
      "data_compliance": [
        {
          "type": "gdpr",
          "requires_consent": false,
          "requires_processing_consent": false,
          "requires_retention_consent": false,
          "retention_period": null,
          "demographic_data_consent_applies": false
        }
      ],
      "internal_job_id": 6408800002,
      "location": {
        "name": "Brisbane, California, United States"
      },
      "metadata": null,
      "id": 8535319002,
      "updated_at": "2026-05-14T12:15:29-04:00",
      "requisition_id": "550-2617",
      "title": "Director, Regulatory Affairs ",
      "company_name": "Nurix",
      "first_published": "2026-05-04T19:04:11-04:00",
      "language": "en",
      "application_deadline": null
    },
    {
      "absolute_url": "https://job-boards.greenhouse.io/nurix/jobs/8552951002",
      "data_compliance": [
        {
          "type": "gdpr",
          "requires_consent": false,
          "requires_processing_consent": false,
          "requires_retention_consent": false,
          "retention_period": null,
          "demographic_data_consent_applies": false
        }
      ],
      "internal_job_id": 6416230002,
      "location": {
        "name": "Brisbane, CA "
      },
      "metadata": null,
      "id": 8552951002,
      "updated_at": "2026-05-15T18:26:21-04:00",
      "requisition_id": "521-2631",
      "title": "Drug Safety Physician",
      "company_name": "Nurix",
      "first_published": "2026-05-15T18:26:21-04:00",
      "language": "en",
      "application_deadline": null
    },
    {
      "absolute_url": "https://job-boards.greenhouse.io/nurix/jobs/8476989002",
      "data_compliance": [
        {
          "type": "gdpr",
          "requires_consent": false,
          "requires_processing_consent": false,
          "requires_retention_consent": false,
          "retention_period": null,
          "demographic_data_consent_applies": false
        }
      ],
      "internal_job_id": 6386012002,
      "location": {
        "name": "Houston, TX"
      },
      "metadata": null,
      "id": 8476989002,
      "updated_at": "2026-05-13T18:49:48-04:00",
      "requisition_id": null,
      "title": "Principal Scientist - Medicinal Chemistry",
      "company_name": "Nurix",
      "first_published": "2026-03-24T10:47:57-04:00",
      "language": "en",
      "application_deadline": null
    },
    {
      "absolute_url": "https://job-boards.greenhouse.io/nurix/jobs/8546724002",
      "data_compliance": [
        {
          "type": "gdpr",
          "requires_consent": false,
          "requires_processing_consent": false,
          "requires_retention_consent": false,
          "retention_period": null,
          "demographic_data_consent_applies": false
        }
      ],
      "internal_job_id": 6413839002,
      "location": {
        "name": "Brisbane, CA "
      },
      "metadata": null,
      "id": 8546724002,
      "updated_at": "2026-05-12T20:03:47-04:00",
      "requisition_id": null,
      "title": "Scientist, Analytical Development and Quality Control ",
      "company_name": "Nurix",
      "first_published": "2026-05-12T20:03:47-04:00",
      "language": "en",
      "application_deadline": null
    },
    {
      "absolute_url": "https://job-boards.greenhouse.io/nurix/jobs/8501712002",
      "data_compliance": [
        {
          "type": "gdpr",
          "requires_consent": false,
          "requires_processing_consent": false,
          "requires_retention_consent": false,
          "retention_period": null,
          "demographic_data_consent_applies": false
        }
      ],
      "internal_job_id": 6395985002,
      "location": {
        "name": "Brisbane, CA "
      },
      "metadata": null,
      "id": 8501712002,
      "updated_at": "2026-04-28T11:53:02-04:00",
      "requisition_id": null,
      "title": "Scientist I, In Vivo Pharmacology ",
      "company_name": "Nurix",
      "first_published": "2026-04-10T11:34:40-04:00",
      "language": "en",
      "application_deadline": null
    },
    {
      "absolute_url": "https://job-boards.greenhouse.io/nurix/jobs/8550393002",
      "data_compliance": [
        {
          "type": "gdpr",
          "requires_consent": false,
          "requires_processing_consent": false,
          "requires_retention_consent": false,
          "retention_period": null,
          "demographic_data_consent_applies": false
        }
      ],
      "internal_job_id": 6415169002,
      "location": {
        "name": "Brisbane, CA "
      },
      "metadata": null,
      "id": 8550393002,
      "updated_at": "2026-05-15T12:47:33-04:00",
      "requisition_id": "520-2620",
      "title": "Senior Clinical Trial Manager",
      "company_name": "Nurix",
      "first_published": "2026-05-15T12:47:33-04:00",
      "language": "en",
      "application_deadline": null
    },
    {
      "absolute_url": "https://job-boards.greenhouse.io/nurix/jobs/8542231002",
      "data_compliance": [
        {
          "type": "gdpr",
          "requires_consent": false,
          "requires_processing_consent": false,
          "requires_retention_consent": false,
          "retention_period": null,
          "demographic_data_consent_applies": false
        }
      ],
      "internal_job_id": 6411605002,
      "location": {
        "name": "Brisbane, California, United States"
      },
      "metadata": null,
      "id": 8542231002,
      "updated_at": "2026-05-11T15:33:12-04:00",
      "requisition_id": "550-2618",
      "title": "Senior Director, Regulatory Affairs (Strategy, Hematology Oncology)",
      "company_name": "Nurix",
      "first_published": "2026-05-08T21:05:54-04:00",
      "language": "en",
      "application_deadline": null
    },
    {
      "absolute_url": "https://job-boards.greenhouse.io/nurix/jobs/8493600002",
      "data_compliance": [
        {
          "type": "gdpr",
          "requires_consent": false,
          "requires_processing_consent": false,
          "requires_retention_consent": false,
          "retention_period": null,
          "demographic_data_consent_applies": false
        }
      ],
      "internal_job_id": 6392628002,
      "location": {
        "name": "Brisbane, CA"
      },
      "metadata": null,
      "id": 8493600002,
      "updated_at": "2026-05-14T12:21:41-04:00",
      "requisition_id": "560-2613",
      "title": "Senior Manager, Quality Operations",
      "company_name": "Nurix",
      "first_published": "2026-04-03T14:43:19-04:00",
      "language": "en",
      "application_deadline": null
    },
    {
      "absolute_url": "https://job-boards.greenhouse.io/nurix/jobs/8546901002",
      "data_compliance": [
        {
          "type": "gdpr",
          "requires_consent": false,
          "requires_processing_consent": false,
          "requires_retention_consent": false,
          "retention_period": null,
          "demographic_data_consent_applies": false
        }
      ],
      "internal_job_id": 6413923002,
      "location": {
        "name": "Brisbane, CA "
      },
      "metadata": null,
      "id": 8546901002,
      "updated_at": "2026-05-13T00:20:54-04:00",
      "requisition_id": null,
      "title": "Senior Scientist, Analytical Development and Quality Control (Drug Product) ",
      "company_name": "Nurix",
      "first_published": "2026-05-13T00:20:54-04:00",
      "language": "en",
      "application_deadline": null
    },
    {
      "absolute_url": "https://job-boards.greenhouse.io/nurix/jobs/8542236002",
      "data_compliance": [
        {
          "type": "gdpr",
          "requires_consent": false,
          "requires_processing_consent": false,
          "requires_retention_consent": false,
          "retention_period": null,
          "demographic_data_consent_applies": false
        }
      ],
      "internal_job_id": 6411608002,
      "location": {
        "name": "Brisbane, California, United States"
      },
      "metadata": null,
      "id": 8542236002,
      "updated_at": "2026-05-11T16:27:14-04:00",
      "requisition_id": "550-2619",
      "title": "Sr. Director, Head of Regulatory & Medical Writing ",
      "company_name": "Nurix",
      "first_published": "2026-05-08T21:19:20-04:00",
      "language": "en",
      "application_deadline": null
    },
    {
      "absolute_url": "https://job-boards.greenhouse.io/nurix/jobs/8540264002",
      "data_compliance": [
        {
          "type": "gdpr",
          "requires_consent": false,
          "requires_processing_consent": false,
          "requires_retention_consent": false,
          "retention_period": null,
          "demographic_data_consent_applies": false
        }
      ],
      "internal_job_id": 6410782002,
      "location": {
        "name": "Brisbane, CA"
      },
      "metadata": null,
      "id": 8540264002,
      "updated_at": "2026-05-12T12:23:43-04:00",
      "requisition_id": null,
      "title": "Vice President, Head of Alliance Management and Program Management",
      "company_name": "Nurix",
      "first_published": "2026-05-07T17:08:55-04:00",
      "language": "en",
      "application_deadline": null
    }
  ]
}