{
  "company": "relaygraduateschoolofeducation",
  "fetched_at": "2026-01-01T04:29:54.674106",
  "job_count": 5,
  "jobs": [
    {
      "absolute_url": "https://job-boards.greenhouse.io/relaygraduateschoolofeducation/jobs/7210934",
      "data_compliance": [
        {
          "type": "gdpr",
          "requires_consent": false,
          "requires_processing_consent": false,
          "requires_retention_consent": false,
          "retention_period": null,
          "demographic_data_consent_applies": false
        }
      ],
      "internal_job_id": 3233990,
      "location": {
        "name": "Flexible within the US"
      },
      "metadata": [
        {
          "id": 131489,
          "name": "Employment Type",
          "value": "Full-Time",
          "value_type": "single_select"
        },
        {
          "id": 142409,
          "name": "Target Start Date",
          "value": "",
          "value_type": "date"
        },
        {
          "id": 26189662,
          "name": "Unit4 Position ID",
          "value": null,
          "value_type": "short_text"
        }
      ],
      "id": 7210934,
      "updated_at": "2025-12-01T15:52:17-05:00",
      "requisition_id": null,
      "title": "Account Executive, Partnerships",
      "company_name": "Relay Graduate School of Education",
      "first_published": "2025-09-02T21:52:06-04:00",
      "language": "en"
    },
    {
      "absolute_url": "https://job-boards.greenhouse.io/relaygraduateschoolofeducation/jobs/7485374",
      "data_compliance": [
        {
          "type": "gdpr",
          "requires_consent": false,
          "requires_processing_consent": false,
          "requires_retention_consent": false,
          "retention_period": null,
          "demographic_data_consent_applies": false
        }
      ],
      "internal_job_id": 3321624,
      "location": {
        "name": "Flexible within the US"
      },
      "metadata": [
        {
          "id": 131489,
          "name": "Employment Type",
          "value": "Full-Time",
          "value_type": "single_select"
        },
        {
          "id": 142409,
          "name": "Target Start Date",
          "value": "",
          "value_type": "date"
        },
        {
          "id": 26189662,
          "name": "Unit4 Position ID",
          "value": null,
          "value_type": "short_text"
        }
      ],
      "id": 7485374,
      "updated_at": "2025-12-18T17:26:58-05:00",
      "requisition_id": null,
      "title": "Associate Partner, National Academies",
      "company_name": "Relay Graduate School of Education",
      "first_published": "2025-12-18T17:26:58-05:00",
      "language": "en"
    },
    {
      "absolute_url": "https://job-boards.greenhouse.io/relaygraduateschoolofeducation/jobs/795611",
      "data_compliance": [
        {
          "type": "gdpr",
          "requires_consent": false,
          "requires_processing_consent": false,
          "requires_retention_consent": false,
          "retention_period": null,
          "demographic_data_consent_applies": false
        }
      ],
      "internal_job_id": 536207,
      "location": {
        "name": "Various Locations "
      },
      "metadata": [
        {
          "id": 131489,
          "name": "Employment Type",
          "value": "Full-Time",
          "value_type": "single_select"
        },
        {
          "id": 142409,
          "name": "Target Start Date",
          "value": "2019-06-30",
          "value_type": "date"
        },
        {
          "id": 26189662,
          "name": "Unit4 Position ID",
          "value": null,
          "value_type": "short_text"
        }
      ],
      "id": 795611,
      "updated_at": "2025-11-03T12:36:12-05:00",
      "requisition_id": null,
      "title": "Future Opportunities",
      "company_name": "Relay Graduate School of Education",
      "first_published": "2019-04-30T17:40:46-04:00",
      "language": "en"
    },
    {
      "absolute_url": "https://job-boards.greenhouse.io/relaygraduateschoolofeducation/jobs/7383655",
      "data_compliance": [
        {
          "type": "gdpr",
          "requires_consent": false,
          "requires_processing_consent": false,
          "requires_retention_consent": false,
          "retention_period": null,
          "demographic_data_consent_applies": false
        }
      ],
      "internal_job_id": 3291300,
      "location": {
        "name": "Flexible within the US"
      },
      "metadata": [
        {
          "id": 131489,
          "name": "Employment Type",
          "value": "Full-Time",
          "value_type": "single_select"
        },
        {
          "id": 142409,
          "name": "Target Start Date",
          "value": "",
          "value_type": "date"
        },
        {
          "id": 26189662,
          "name": "Unit4 Position ID",
          "value": null,
          "value_type": "short_text"
        }
      ],
      "id": 7383655,
      "updated_at": "2025-11-19T13:35:53-05:00",
      "requisition_id": null,
      "title": "Professor, Curriculum Design, Culturally and Linguistically Diverse Learners",
      "company_name": "Relay Graduate School of Education",
      "first_published": "2025-11-07T12:24:32-05:00",
      "language": "en"
    },
    {
      "absolute_url": "https://job-boards.greenhouse.io/relaygraduateschoolofeducation/jobs/7353463",
      "data_compliance": [
        {
          "type": "gdpr",
          "requires_consent": false,
          "requires_processing_consent": false,
          "requires_retention_consent": false,
          "retention_period": null,
          "demographic_data_consent_applies": false
        }
      ],
      "internal_job_id": 3279957,
      "location": {
        "name": "New York, NY"
      },
      "metadata": [
        {
          "id": 131489,
          "name": "Employment Type",
          "value": "Full-Time",
          "value_type": "single_select"
        },
        {
          "id": 142409,
          "name": "Target Start Date",
          "value": "",
          "value_type": "date"
        },
        {
          "id": 26189662,
          "name": "Unit4 Position ID",
          "value": null,
          "value_type": "short_text"
        }
      ],
      "id": 7353463,
      "updated_at": "2025-12-05T10:39:51-05:00",
      "requisition_id": null,
      "title": "Professor, New York Clinical Practice",
      "company_name": "Relay Graduate School of Education",
      "first_published": "2025-10-24T11:12:30-04:00",
      "language": "en"
    }
  ]
}